[
  {
    "seed": 69,
    "B": 2,
    "mc_idx": 0,
    "G": 0.1902151107788086,
    "A": 0.233917236328125,
    "residual": -0.043702125549316406,
    "schedule_steps": [
      41,
      59
    ]
  },
  {
    "seed": 69,
    "B": 2,
    "mc_idx": 1,
    "G": 0.32309627532958984,
    "A": 0.3123779296875,
    "residual": 0.010718345642089844,
    "schedule_steps": [
      19,
      39
    ]
  },
  {
    "seed": 69,
    "B": 2,
    "mc_idx": 2,
    "G": 0.23003625869750977,
    "A": 0.23387861251831055,
    "residual": -0.0038423538208007812,
    "schedule_steps": [
      18,
      26
    ]
  },
  {
    "seed": 69,
    "B": 2,
    "mc_idx": 3,
    "G": 0.16777467727661133,
    "A": 0.12136125564575195,
    "residual": 0.046413421630859375,
    "schedule_steps": [
      44,
      45
    ]
  },
  {
    "seed": 69,
    "B": 2,
    "mc_idx": 4,
    "G": 0.13581466674804688,
    "A": 0.23505544662475586,
    "residual": -0.09924077987670898,
    "schedule_steps": [
      18,
      52
    ]
  },
  {
    "seed": 69,
    "B": 2,
    "mc_idx": 5,
    "G": 0.24669408798217773,
    "A": 0.3074774742126465,
    "residual": -0.06078338623046875,
    "schedule_steps": [
      6,
      61
    ]
  },
  {
    "seed": 69,
    "B": 2,
    "mc_idx": 6,
    "G": 0.21306467056274414,
    "A": 0.4845900535583496,
    "residual": -0.27152538299560547,
    "schedule_steps": [
      12,
      13
    ]
  },
  {
    "seed": 69,
    "B": 2,
    "mc_idx": 7,
    "G": 0.28292226791381836,
    "A": 0.28249168395996094,
    "residual": 0.0004305839538574219,
    "schedule_steps": [
      3,
      57
    ]
  },
  {
    "seed": 69,
    "B": 2,
    "mc_idx": 8,
    "G": 0.28026866912841797,
    "A": 0.3391704559326172,
    "residual": -0.05890178680419922,
    "schedule_steps": [
      10,
      34
    ]
  },
  {
    "seed": 69,
    "B": 2,
    "mc_idx": 9,
    "G": 0.17147159576416016,
    "A": 0.10749149322509766,
    "residual": 0.0639801025390625,
    "schedule_steps": [
      26,
      63
    ]
  },
  {
    "seed": 69,
    "B": 2,
    "mc_idx": 10,
    "G": -0.06137418746948242,
    "A": -0.011099815368652344,
    "residual": -0.05027437210083008,
    "schedule_steps": [
      0,
      17
    ]
  },
  {
    "seed": 69,
    "B": 2,
    "mc_idx": 11,
    "G": 0.20536518096923828,
    "A": 0.21763134002685547,
    "residual": -0.012266159057617188,
    "schedule_steps": [
      13,
      41
    ]
  },
  {
    "seed": 69,
    "B": 2,
    "mc_idx": 12,
    "G": 0.37400102615356445,
    "A": 0.42840099334716797,
    "residual": -0.054399967193603516,
    "schedule_steps": [
      11,
      61
    ]
  },
  {
    "seed": 69,
    "B": 2,
    "mc_idx": 13,
    "G": 0.08634424209594727,
    "A": 0.29160022735595703,
    "residual": -0.20525598526000977,
    "schedule_steps": [
      0,
      11
    ]
  },
  {
    "seed": 69,
    "B": 2,
    "mc_idx": 14,
    "G": 0.14473962783813477,
    "A": 0.14407110214233398,
    "residual": 0.0006685256958007812,
    "schedule_steps": [
      13,
      27
    ]
  },
  {
    "seed": 69,
    "B": 2,
    "mc_idx": 15,
    "G": 0.28108978271484375,
    "A": 0.16441583633422852,
    "residual": 0.11667394638061523,
    "schedule_steps": [
      17,
      38
    ]
  },
  {
    "seed": 69,
    "B": 2,
    "mc_idx": 16,
    "G": 0.23620223999023438,
    "A": 0.28247928619384766,
    "residual": -0.04627704620361328,
    "schedule_steps": [
      23,
      45
    ]
  },
  {
    "seed": 69,
    "B": 2,
    "mc_idx": 17,
    "G": 0.05717658996582031,
    "A": 0.09711217880249023,
    "residual": -0.03993558883666992,
    "schedule_steps": [
      51,
      53
    ]
  },
  {
    "seed": 69,
    "B": 2,
    "mc_idx": 18,
    "G": 0.14415454864501953,
    "A": 0.21732425689697266,
    "residual": -0.07316970825195312,
    "schedule_steps": [
      10,
      60
    ]
  },
  {
    "seed": 69,
    "B": 2,
    "mc_idx": 19,
    "G": 0.2585625648498535,
    "A": 0.2825465202331543,
    "residual": -0.02398395538330078,
    "schedule_steps": [
      16,
      53
    ]
  },
  {
    "seed": 69,
    "B": 2,
    "mc_idx": 20,
    "G": 0.0933985710144043,
    "A": 0.0820765495300293,
    "residual": 0.011322021484375,
    "schedule_steps": [
      29,
      54
    ]
  },
  {
    "seed": 69,
    "B": 2,
    "mc_idx": 21,
    "G": 0.14490604400634766,
    "A": 0.07927083969116211,
    "residual": 0.06563520431518555,
    "schedule_steps": [
      0,
      36
    ]
  },
  {
    "seed": 69,
    "B": 2,
    "mc_idx": 22,
    "G": 0.14316225051879883,
    "A": 0.21483707427978516,
    "residual": -0.07167482376098633,
    "schedule_steps": [
      30,
      36
    ]
  },
  {
    "seed": 69,
    "B": 2,
    "mc_idx": 23,
    "G": 0.06643915176391602,
    "A": 0.14183282852172852,
    "residual": -0.0753936767578125,
    "schedule_steps": [
      44,
      61
    ]
  },
  {
    "seed": 69,
    "B": 2,
    "mc_idx": 24,
    "G": 0.21420574188232422,
    "A": 0.298922061920166,
    "residual": -0.0847163200378418,
    "schedule_steps": [
      19,
      58
    ]
  },
  {
    "seed": 69,
    "B": 2,
    "mc_idx": 25,
    "G": 0.14578628540039062,
    "A": 0.15925836563110352,
    "residual": -0.01347208023071289,
    "schedule_steps": [
      45,
      57
    ]
  },
  {
    "seed": 69,
    "B": 2,
    "mc_idx": 26,
    "G": 0.22876262664794922,
    "A": 0.19951677322387695,
    "residual": 0.029245853424072266,
    "schedule_steps": [
      41,
      51
    ]
  },
  {
    "seed": 69,
    "B": 2,
    "mc_idx": 27,
    "G": 0.09638023376464844,
    "A": 0.1600813865661621,
    "residual": -0.06370115280151367,
    "schedule_steps": [
      35,
      61
    ]
  },
  {
    "seed": 69,
    "B": 2,
    "mc_idx": 28,
    "G": 0.28574323654174805,
    "A": 0.13848447799682617,
    "residual": 0.14725875854492188,
    "schedule_steps": [
      17,
      36
    ]
  },
  {
    "seed": 69,
    "B": 2,
    "mc_idx": 29,
    "G": -0.09891557693481445,
    "A": 0.054360389709472656,
    "residual": -0.1532759666442871,
    "schedule_steps": [
      0,
      48
    ]
  },
  {
    "seed": 69,
    "B": 2,
    "mc_idx": 30,
    "G": 0.22581243515014648,
    "A": 0.11114311218261719,
    "residual": 0.1146693229675293,
    "schedule_steps": [
      26,
      46
    ]
  },
  {
    "seed": 69,
    "B": 2,
    "mc_idx": 31,
    "G": 0.26264286041259766,
    "A": 0.25163841247558594,
    "residual": 0.011004447937011719,
    "schedule_steps": [
      10,
      40
    ]
  },
  {
    "seed": 69,
    "B": 2,
    "mc_idx": 32,
    "G": 0.1004323959350586,
    "A": 0.1343989372253418,
    "residual": -0.0339665412902832,
    "schedule_steps": [
      44,
      49
    ]
  },
  {
    "seed": 69,
    "B": 2,
    "mc_idx": 33,
    "G": 0.3120608329772949,
    "A": 0.4518113136291504,
    "residual": -0.13975048065185547,
    "schedule_steps": [
      8,
      12
    ]
  },
  {
    "seed": 69,
    "B": 2,
    "mc_idx": 34,
    "G": 0.1621246337890625,
    "A": 0.2750372886657715,
    "residual": -0.11291265487670898,
    "schedule_steps": [
      13,
      23
    ]
  },
  {
    "seed": 69,
    "B": 2,
    "mc_idx": 35,
    "G": 0.10026264190673828,
    "A": 0.14751148223876953,
    "residual": -0.04724884033203125,
    "schedule_steps": [
      13,
      60
    ]
  },
  {
    "seed": 69,
    "B": 2,
    "mc_idx": 36,
    "G": 0.2603592872619629,
    "A": 0.34476470947265625,
    "residual": -0.08440542221069336,
    "schedule_steps": [
      3,
      38
    ]
  },
  {
    "seed": 69,
    "B": 2,
    "mc_idx": 37,
    "G": 0.04698753356933594,
    "A": 0.002064228057861328,
    "residual": 0.04492330551147461,
    "schedule_steps": [
      28,
      32
    ]
  },
  {
    "seed": 69,
    "B": 2,
    "mc_idx": 38,
    "G": 0.21519756317138672,
    "A": 0.21452045440673828,
    "residual": 0.0006771087646484375,
    "schedule_steps": [
      19,
      55
    ]
  },
  {
    "seed": 69,
    "B": 2,
    "mc_idx": 39,
    "G": 0.1785879135131836,
    "A": 0.30171632766723633,
    "residual": -0.12312841415405273,
    "schedule_steps": [
      23,
      30
    ]
  },
  {
    "seed": 69,
    "B": 2,
    "mc_idx": 40,
    "G": 0.18413782119750977,
    "A": 0.23337793350219727,
    "residual": -0.0492401123046875,
    "schedule_steps": [
      21,
      33
    ]
  },
  {
    "seed": 69,
    "B": 2,
    "mc_idx": 41,
    "G": 0.2699580192565918,
    "A": 0.6063551902770996,
    "residual": -0.3363971710205078,
    "schedule_steps": [
      4,
      6
    ]
  },
  {
    "seed": 69,
    "B": 2,
    "mc_idx": 42,
    "G": 0.11979246139526367,
    "A": 0.22208786010742188,
    "residual": -0.1022953987121582,
    "schedule_steps": [
      29,
      34
    ]
  },
  {
    "seed": 69,
    "B": 2,
    "mc_idx": 43,
    "G": 0.08292818069458008,
    "A": 0.09973001480102539,
    "residual": -0.016801834106445312,
    "schedule_steps": [
      55,
      63
    ]
  },
  {
    "seed": 69,
    "B": 2,
    "mc_idx": 44,
    "G": 0.4724869728088379,
    "A": 0.5429158210754395,
    "residual": -0.07042884826660156,
    "schedule_steps": [
      7,
      49
    ]
  },
  {
    "seed": 69,
    "B": 2,
    "mc_idx": 45,
    "G": 0.20986127853393555,
    "A": 0.19695329666137695,
    "residual": 0.012907981872558594,
    "schedule_steps": [
      41,
      63
    ]
  },
  {
    "seed": 69,
    "B": 2,
    "mc_idx": 46,
    "G": 0.12117147445678711,
    "A": 0.13646841049194336,
    "residual": -0.01529693603515625,
    "schedule_steps": [
      13,
      62
    ]
  },
  {
    "seed": 69,
    "B": 2,
    "mc_idx": 47,
    "G": 0.23399114608764648,
    "A": 0.28807830810546875,
    "residual": -0.054087162017822266,
    "schedule_steps": [
      10,
      39
    ]
  },
  {
    "seed": 69,
    "B": 2,
    "mc_idx": 48,
    "G": 0.2022695541381836,
    "A": 0.12141561508178711,
    "residual": 0.08085393905639648,
    "schedule_steps": [
      14,
      63
    ]
  },
  {
    "seed": 69,
    "B": 2,
    "mc_idx": 49,
    "G": 0.17850017547607422,
    "A": 0.16216611862182617,
    "residual": 0.016334056854248047,
    "schedule_steps": [
      31,
      33
    ]
  },
  {
    "seed": 69,
    "B": 2,
    "mc_idx": 50,
    "G": 0.1587815284729004,
    "A": 0.1349167823791504,
    "residual": 0.02386474609375,
    "schedule_steps": [
      42,
      60
    ]
  },
  {
    "seed": 69,
    "B": 2,
    "mc_idx": 51,
    "G": 0.05396890640258789,
    "A": 0.11123180389404297,
    "residual": -0.05726289749145508,
    "schedule_steps": [
      52,
      54
    ]
  },
  {
    "seed": 69,
    "B": 2,
    "mc_idx": 52,
    "G": -0.08662128448486328,
    "A": -0.10207414627075195,
    "residual": 0.015452861785888672,
    "schedule_steps": [
      0,
      47
    ]
  },
  {
    "seed": 69,
    "B": 2,
    "mc_idx": 53,
    "G": 0.10282516479492188,
    "A": 0.19007158279418945,
    "residual": -0.08724641799926758,
    "schedule_steps": [
      5,
      39
    ]
  },
  {
    "seed": 69,
    "B": 2,
    "mc_idx": 54,
    "G": 0.12349700927734375,
    "A": 0.13678836822509766,
    "residual": -0.013291358947753906,
    "schedule_steps": [
      45,
      51
    ]
  },
  {
    "seed": 69,
    "B": 2,
    "mc_idx": 55,
    "G": 0.0844721794128418,
    "A": 0.17028379440307617,
    "residual": -0.08581161499023438,
    "schedule_steps": [
      28,
      43
    ]
  },
  {
    "seed": 69,
    "B": 2,
    "mc_idx": 56,
    "G": 0.055615901947021484,
    "A": 0.055615901947021484,
    "residual": 0.0,
    "schedule_steps": [
      1,
      52
    ]
  },
  {
    "seed": 69,
    "B": 2,
    "mc_idx": 57,
    "G": 0.17544317245483398,
    "A": 0.11824750900268555,
    "residual": 0.05719566345214844,
    "schedule_steps": [
      25,
      32
    ]
  },
  {
    "seed": 69,
    "B": 2,
    "mc_idx": 58,
    "G": 0.19371986389160156,
    "A": 0.26244258880615234,
    "residual": -0.06872272491455078,
    "schedule_steps": [
      23,
      42
    ]
  },
  {
    "seed": 69,
    "B": 2,
    "mc_idx": 59,
    "G": -0.07983589172363281,
    "A": 0.16638660430908203,
    "residual": -0.24622249603271484,
    "schedule_steps": [
      20,
      34
    ]
  },
  {
    "seed": 69,
    "B": 2,
    "mc_idx": 60,
    "G": 0.21519756317138672,
    "A": 0.21452045440673828,
    "residual": 0.0006771087646484375,
    "schedule_steps": [
      19,
      55
    ]
  },
  {
    "seed": 69,
    "B": 2,
    "mc_idx": 61,
    "G": 0.1829991340637207,
    "A": 0.2456345558166504,
    "residual": -0.06263542175292969,
    "schedule_steps": [
      24,
      36
    ]
  },
  {
    "seed": 69,
    "B": 2,
    "mc_idx": 62,
    "G": -0.06137418746948242,
    "A": -0.011099815368652344,
    "residual": -0.05027437210083008,
    "schedule_steps": [
      0,
      17
    ]
  },
  {
    "seed": 69,
    "B": 2,
    "mc_idx": 63,
    "G": 0.23466205596923828,
    "A": 0.18239593505859375,
    "residual": 0.05226612091064453,
    "schedule_steps": [
      2,
      40
    ]
  },
  {
    "seed": 69,
    "B": 2,
    "mc_idx": 64,
    "G": 0.06378555297851562,
    "A": 0.06378555297851562,
    "residual": 0.0,
    "schedule_steps": [
      1,
      15
    ]
  },
  {
    "seed": 69,
    "B": 2,
    "mc_idx": 65,
    "G": 0.16160869598388672,
    "A": 0.039601802825927734,
    "residual": 0.12200689315795898,
    "schedule_steps": [
      37,
      47
    ]
  },
  {
    "seed": 69,
    "B": 2,
    "mc_idx": 66,
    "G": 0.4685802459716797,
    "A": 0.5799612998962402,
    "residual": -0.11138105392456055,
    "schedule_steps": [
      4,
      18
    ]
  },
  {
    "seed": 69,
    "B": 2,
    "mc_idx": 67,
    "G": 0.18346595764160156,
    "A": 0.17036151885986328,
    "residual": 0.013104438781738281,
    "schedule_steps": [
      29,
      41
    ]
  },
  {
    "seed": 69,
    "B": 2,
    "mc_idx": 68,
    "G": 0.20685577392578125,
    "A": 0.18539714813232422,
    "residual": 0.02145862579345703,
    "schedule_steps": [
      41,
      53
    ]
  },
  {
    "seed": 69,
    "B": 2,
    "mc_idx": 69,
    "G": 0.1516127586364746,
    "A": 0.11418819427490234,
    "residual": 0.037424564361572266,
    "schedule_steps": [
      42,
      63
    ]
  },
  {
    "seed": 69,
    "B": 2,
    "mc_idx": 70,
    "G": 0.019070148468017578,
    "A": 0.15065288543701172,
    "residual": -0.13158273696899414,
    "schedule_steps": [
      42,
      48
    ]
  },
  {
    "seed": 69,
    "B": 2,
    "mc_idx": 71,
    "G": 0.03228139877319336,
    "A": 0.01094818115234375,
    "residual": 0.02133321762084961,
    "schedule_steps": [
      20,
      44
    ]
  },
  {
    "seed": 69,
    "B": 2,
    "mc_idx": 72,
    "G": 0.5356407165527344,
    "A": 0.6443328857421875,
    "residual": -0.10869216918945312,
    "schedule_steps": [
      7,
      34
    ]
  },
  {
    "seed": 69,
    "B": 2,
    "mc_idx": 73,
    "G": 0.18343544006347656,
    "A": 0.19560003280639648,
    "residual": -0.012164592742919922,
    "schedule_steps": [
      36,
      45
    ]
  },
  {
    "seed": 69,
    "B": 2,
    "mc_idx": 74,
    "G": 0.18321847915649414,
    "A": 0.2532205581665039,
    "residual": -0.07000207901000977,
    "schedule_steps": [
      18,
      60
    ]
  },
  {
    "seed": 69,
    "B": 2,
    "mc_idx": 75,
    "G": 0.2421431541442871,
    "A": 0.10997295379638672,
    "residual": 0.1321702003479004,
    "schedule_steps": [
      31,
      51
    ]
  },
  {
    "seed": 69,
    "B": 2,
    "mc_idx": 76,
    "G": 0.07378101348876953,
    "A": 0.07378101348876953,
    "residual": 0.0,
    "schedule_steps": [
      1,
      60
    ]
  },
  {
    "seed": 69,
    "B": 2,
    "mc_idx": 77,
    "G": 0.18829965591430664,
    "A": 0.33251380920410156,
    "residual": -0.14421415328979492,
    "schedule_steps": [
      23,
      24
    ]
  },
  {
    "seed": 69,
    "B": 2,
    "mc_idx": 78,
    "G": 0.1524653434753418,
    "A": 0.13215208053588867,
    "residual": 0.020313262939453125,
    "schedule_steps": [
      17,
      40
    ]
  },
  {
    "seed": 69,
    "B": 2,
    "mc_idx": 79,
    "G": 0.21256256103515625,
    "A": 0.12506723403930664,
    "residual": 0.08749532699584961,
    "schedule_steps": [
      14,
      46
    ]
  },
  {
    "seed": 69,
    "B": 2,
    "mc_idx": 80,
    "G": -0.028840065002441406,
    "A": -0.011301517486572266,
    "residual": -0.01753854751586914,
    "schedule_steps": [
      47,
      54
    ]
  },
  {
    "seed": 69,
    "B": 2,
    "mc_idx": 81,
    "G": 0.3096489906311035,
    "A": 0.23452377319335938,
    "residual": 0.07512521743774414,
    "schedule_steps": [
      3,
      56
    ]
  },
  {
    "seed": 69,
    "B": 2,
    "mc_idx": 82,
    "G": 0.1658153533935547,
    "A": 0.10115242004394531,
    "residual": 0.06466293334960938,
    "schedule_steps": [
      5,
      51
    ]
  },
  {
    "seed": 69,
    "B": 2,
    "mc_idx": 83,
    "G": 0.23399114608764648,
    "A": 0.28807830810546875,
    "residual": -0.054087162017822266,
    "schedule_steps": [
      10,
      39
    ]
  },
  {
    "seed": 69,
    "B": 2,
    "mc_idx": 84,
    "G": 0.13308954238891602,
    "A": 0.27707910537719727,
    "residual": -0.14398956298828125,
    "schedule_steps": [
      40,
      43
    ]
  },
  {
    "seed": 69,
    "B": 2,
    "mc_idx": 85,
    "G": 0.20060157775878906,
    "A": 0.1282200813293457,
    "residual": 0.07238149642944336,
    "schedule_steps": [
      26,
      60
    ]
  },
  {
    "seed": 69,
    "B": 2,
    "mc_idx": 86,
    "G": 0.08725357055664062,
    "A": 0.30483579635620117,
    "residual": -0.21758222579956055,
    "schedule_steps": [
      15,
      16
    ]
  },
  {
    "seed": 69,
    "B": 2,
    "mc_idx": 87,
    "G": 0.5421223640441895,
    "A": 0.3678750991821289,
    "residual": 0.17424726486206055,
    "schedule_steps": [
      6,
      9
    ]
  },
  {
    "seed": 69,
    "B": 2,
    "mc_idx": 88,
    "G": 0.20184946060180664,
    "A": 0.2585010528564453,
    "residual": -0.05665159225463867,
    "schedule_steps": [
      43,
      48
    ]
  },
  {
    "seed": 69,
    "B": 2,
    "mc_idx": 89,
    "G": 0.15354681015014648,
    "A": 0.16878461837768555,
    "residual": -0.015237808227539062,
    "schedule_steps": [
      31,
      36
    ]
  },
  {
    "seed": 69,
    "B": 2,
    "mc_idx": 90,
    "G": 0.5322842597961426,
    "A": 0.3817882537841797,
    "residual": 0.1504960060119629,
    "schedule_steps": [
      7,
      47
    ]
  },
  {
    "seed": 69,
    "B": 2,
    "mc_idx": 91,
    "G": 0.4088706970214844,
    "A": 0.4900388717651367,
    "residual": -0.08116817474365234,
    "schedule_steps": [
      4,
      48
    ]
  },
  {
    "seed": 69,
    "B": 2,
    "mc_idx": 92,
    "G": 0.5454502105712891,
    "A": 0.5001273155212402,
    "residual": 0.04532289505004883,
    "schedule_steps": [
      12,
      22
    ]
  },
  {
    "seed": 69,
    "B": 2,
    "mc_idx": 93,
    "G": 0.0958409309387207,
    "A": 0.1911611557006836,
    "residual": -0.09532022476196289,
    "schedule_steps": [
      48,
      61
    ]
  },
  {
    "seed": 69,
    "B": 2,
    "mc_idx": 94,
    "G": 0.15831232070922852,
    "A": 0.1444554328918457,
    "residual": 0.013856887817382812,
    "schedule_steps": [
      26,
      59
    ]
  },
  {
    "seed": 69,
    "B": 2,
    "mc_idx": 95,
    "G": 0.07782602310180664,
    "A": 0.07710933685302734,
    "residual": 0.0007166862487792969,
    "schedule_steps": [
      17,
      63
    ]
  },
  {
    "seed": 69,
    "B": 2,
    "mc_idx": 96,
    "G": 0.03804969787597656,
    "A": 0.15534591674804688,
    "residual": -0.11729621887207031,
    "schedule_steps": [
      42,
      49
    ]
  },
  {
    "seed": 69,
    "B": 2,
    "mc_idx": 97,
    "G": 0.29047489166259766,
    "A": 0.11525249481201172,
    "residual": 0.17522239685058594,
    "schedule_steps": [
      2,
      8
    ]
  },
  {
    "seed": 69,
    "B": 2,
    "mc_idx": 98,
    "G": 0.2114238739013672,
    "A": 0.11826705932617188,
    "residual": 0.09315681457519531,
    "schedule_steps": [
      17,
      49
    ]
  },
  {
    "seed": 69,
    "B": 2,
    "mc_idx": 99,
    "G": 0.27942323684692383,
    "A": 0.43456602096557617,
    "residual": -0.15514278411865234,
    "schedule_steps": [
      11,
      33
    ]
  },
  {
    "seed": 69,
    "B": 3,
    "mc_idx": 0,
    "G": 0.5718674659729004,
    "A": 0.5219779014587402,
    "residual": 0.049889564514160156,
    "schedule_steps": [
      12,
      20,
      38
    ]
  },
  {
    "seed": 69,
    "B": 3,
    "mc_idx": 1,
    "G": 0.2591266632080078,
    "A": 0.3707561492919922,
    "residual": -0.11162948608398438,
    "schedule_steps": [
      16,
      44,
      48
    ]
  },
  {
    "seed": 69,
    "B": 3,
    "mc_idx": 2,
    "G": 0.32796573638916016,
    "A": 0.31418848037719727,
    "residual": 0.01377725601196289,
    "schedule_steps": [
      16,
      29,
      55
    ]
  },
  {
    "seed": 69,
    "B": 3,
    "mc_idx": 3,
    "G": 0.41024208068847656,
    "A": 0.61016845703125,
    "residual": -0.19992637634277344,
    "schedule_steps": [
      11,
      36,
      43
    ]
  },
  {
    "seed": 69,
    "B": 3,
    "mc_idx": 4,
    "G": 0.29125452041625977,
    "A": 0.29920339584350586,
    "residual": -0.007948875427246094,
    "schedule_steps": [
      8,
      22,
      43
    ]
  },
  {
    "seed": 69,
    "B": 3,
    "mc_idx": 5,
    "G": 0.08963394165039062,
    "A": 0.2280564308166504,
    "residual": -0.13842248916625977,
    "schedule_steps": [
      50,
      55,
      57
    ]
  },
  {
    "seed": 69,
    "B": 3,
    "mc_idx": 6,
    "G": 0.22130393981933594,
    "A": 0.31022167205810547,
    "residual": -0.08891773223876953,
    "schedule_steps": [
      30,
      37,
      50
    ]
  },
  {
    "seed": 69,
    "B": 3,
    "mc_idx": 7,
    "G": 0.17268085479736328,
    "A": 0.11519193649291992,
    "residual": 0.05748891830444336,
    "schedule_steps": [
      1,
      32,
      36
    ]
  },
  {
    "seed": 69,
    "B": 3,
    "mc_idx": 8,
    "G": 0.09947681427001953,
    "A": 0.263852596282959,
    "residual": -0.16437578201293945,
    "schedule_steps": [
      5,
      39,
      60
    ]
  },
  {
    "seed": 69,
    "B": 3,
    "mc_idx": 9,
    "G": 0.31210756301879883,
    "A": 0.2732968330383301,
    "residual": 0.03881072998046875,
    "schedule_steps": [
      10,
      29,
      50
    ]
  },
  {
    "seed": 69,
    "B": 3,
    "mc_idx": 10,
    "G": -0.04955244064331055,
    "A": 0.09668684005737305,
    "residual": -0.1462392807006836,
    "schedule_steps": [
      0,
      32,
      58
    ]
  },
  {
    "seed": 69,
    "B": 3,
    "mc_idx": 11,
    "G": 0.597567081451416,
    "A": 0.5009803771972656,
    "residual": 0.09658670425415039,
    "schedule_steps": [
      4,
      27,
      56
    ]
  },
  {
    "seed": 69,
    "B": 3,
    "mc_idx": 12,
    "G": 0.5899658203125,
    "A": 0.4434218406677246,
    "residual": 0.1465439796447754,
    "schedule_steps": [
      3,
      24,
      33
    ]
  },
  {
    "seed": 69,
    "B": 3,
    "mc_idx": 13,
    "G": 0.14528703689575195,
    "A": 0.2457408905029297,
    "residual": -0.10045385360717773,
    "schedule_steps": [
      37,
      42,
      57
    ]
  },
  {
    "seed": 69,
    "B": 3,
    "mc_idx": 14,
    "G": 0.06408357620239258,
    "A": 0.13903045654296875,
    "residual": -0.07494688034057617,
    "schedule_steps": [
      0,
      25,
      46
    ]
  },
  {
    "seed": 69,
    "B": 3,
    "mc_idx": 15,
    "G": 0.533599853515625,
    "A": 0.3976411819458008,
    "residual": 0.13595867156982422,
    "schedule_steps": [
      2,
      18,
      41
    ]
  },
  {
    "seed": 69,
    "B": 3,
    "mc_idx": 16,
    "G": 0.5948457717895508,
    "A": 0.5654783248901367,
    "residual": 0.029367446899414062,
    "schedule_steps": [
      4,
      35,
      37
    ]
  },
  {
    "seed": 69,
    "B": 3,
    "mc_idx": 17,
    "G": 0.6149249076843262,
    "A": 0.6387052536010742,
    "residual": -0.023780345916748047,
    "schedule_steps": [
      4,
      19,
      27
    ]
  },
  {
    "seed": 69,
    "B": 3,
    "mc_idx": 18,
    "G": 0.2579216957092285,
    "A": 0.18484210968017578,
    "residual": 0.07307958602905273,
    "schedule_steps": [
      31,
      46,
      60
    ]
  },
  {
    "seed": 69,
    "B": 3,
    "mc_idx": 19,
    "G": -0.007836341857910156,
    "A": 0.07007265090942383,
    "residual": -0.07790899276733398,
    "schedule_steps": [
      0,
      17,
      45
    ]
  },
  {
    "seed": 69,
    "B": 3,
    "mc_idx": 20,
    "G": 0.08548879623413086,
    "A": 0.2542715072631836,
    "residual": -0.16878271102905273,
    "schedule_steps": [
      25,
      45,
      51
    ]
  },
  {
    "seed": 69,
    "B": 3,
    "mc_idx": 21,
    "G": 0.4449295997619629,
    "A": 0.28000640869140625,
    "residual": 0.16492319107055664,
    "schedule_steps": [
      2,
      3,
      28
    ]
  },
  {
    "seed": 69,
    "B": 3,
    "mc_idx": 22,
    "G": 0.3128376007080078,
    "A": 0.30605602264404297,
    "residual": 0.006781578063964844,
    "schedule_steps": [
      19,
      40,
      56
    ]
  },
  {
    "seed": 69,
    "B": 3,
    "mc_idx": 23,
    "G": 0.1874227523803711,
    "A": 0.31098318099975586,
    "residual": -0.12356042861938477,
    "schedule_steps": [
      19,
      53,
      61
    ]
  },
  {
    "seed": 69,
    "B": 3,
    "mc_idx": 24,
    "G": 0.5582833290100098,
    "A": 0.7087273597717285,
    "residual": -0.15044403076171875,
    "schedule_steps": [
      3,
      7,
      52
    ]
  },
  {
    "seed": 69,
    "B": 3,
    "mc_idx": 25,
    "G": 0.1658782958984375,
    "A": 0.3191065788269043,
    "residual": -0.1532282829284668,
    "schedule_steps": [
      10,
      36,
      42
    ]
  },
  {
    "seed": 69,
    "B": 3,
    "mc_idx": 26,
    "G": 0.546750545501709,
    "A": 0.5798435211181641,
    "residual": -0.03309297561645508,
    "schedule_steps": [
      1,
      12,
      43
    ]
  },
  {
    "seed": 69,
    "B": 3,
    "mc_idx": 27,
    "G": 0.3301405906677246,
    "A": 0.2584052085876465,
    "residual": 0.07173538208007812,
    "schedule_steps": [
      15,
      30,
      49
    ]
  },
  {
    "seed": 69,
    "B": 3,
    "mc_idx": 28,
    "G": 0.2098226547241211,
    "A": 0.22656536102294922,
    "residual": -0.016742706298828125,
    "schedule_steps": [
      15,
      42,
      61
    ]
  },
  {
    "seed": 69,
    "B": 3,
    "mc_idx": 29,
    "G": 0.40377044677734375,
    "A": 0.4057197570800781,
    "residual": -0.001949310302734375,
    "schedule_steps": [
      18,
      19,
      35
    ]
  },
  {
    "seed": 69,
    "B": 3,
    "mc_idx": 30,
    "G": 0.27490806579589844,
    "A": 0.21062898635864258,
    "residual": 0.06427907943725586,
    "schedule_steps": [
      22,
      44,
      45
    ]
  },
  {
    "seed": 69,
    "B": 3,
    "mc_idx": 31,
    "G": 0.48192787170410156,
    "A": 0.6240801811218262,
    "residual": -0.1421523094177246,
    "schedule_steps": [
      7,
      13,
      61
    ]
  },
  {
    "seed": 69,
    "B": 3,
    "mc_idx": 32,
    "G": 0.09067535400390625,
    "A": 0.2026500701904297,
    "residual": -0.11197471618652344,
    "schedule_steps": [
      5,
      30,
      46
    ]
  },
  {
    "seed": 69,
    "B": 3,
    "mc_idx": 33,
    "G": 0.1500105857849121,
    "A": 0.2848367691040039,
    "residual": -0.1348261833190918,
    "schedule_steps": [
      22,
      25,
      57
    ]
  },
  {
    "seed": 69,
    "B": 3,
    "mc_idx": 34,
    "G": 0.59912109375,
    "A": 0.5644330978393555,
    "residual": 0.03468799591064453,
    "schedule_steps": [
      7,
      28,
      36
    ]
  },
  {
    "seed": 69,
    "B": 3,
    "mc_idx": 35,
    "G": 0.11934900283813477,
    "A": 0.15963077545166016,
    "residual": -0.04028177261352539,
    "schedule_steps": [
      44,
      46,
      62
    ]
  },
  {
    "seed": 69,
    "B": 3,
    "mc_idx": 36,
    "G": 0.10102987289428711,
    "A": 0.20748281478881836,
    "residual": -0.10645294189453125,
    "schedule_steps": [
      51,
      57,
      60
    ]
  },
  {
    "seed": 69,
    "B": 3,
    "mc_idx": 37,
    "G": 0.1616687774658203,
    "A": 0.14051389694213867,
    "residual": 0.02115488052368164,
    "schedule_steps": [
      29,
      35,
      52
    ]
  },
  {
    "seed": 69,
    "B": 3,
    "mc_idx": 38,
    "G": 0.17720413208007812,
    "A": 0.2855854034423828,
    "residual": -0.10838127136230469,
    "schedule_steps": [
      25,
      57,
      59
    ]
  },
  {
    "seed": 69,
    "B": 3,
    "mc_idx": 39,
    "G": 0.1001291275024414,
    "A": 0.24755620956420898,
    "residual": -0.14742708206176758,
    "schedule_steps": [
      29,
      58,
      59
    ]
  },
  {
    "seed": 69,
    "B": 3,
    "mc_idx": 40,
    "G": 0.28108787536621094,
    "A": 0.19545269012451172,
    "residual": 0.08563518524169922,
    "schedule_steps": [
      17,
      24,
      44
    ]
  },
  {
    "seed": 69,
    "B": 3,
    "mc_idx": 41,
    "G": 0.37542009353637695,
    "A": 0.43457603454589844,
    "residual": -0.059155941009521484,
    "schedule_steps": [
      11,
      28,
      37
    ]
  },
  {
    "seed": 69,
    "B": 3,
    "mc_idx": 42,
    "G": 0.1820540428161621,
    "A": 0.2582516670227051,
    "residual": -0.07619762420654297,
    "schedule_steps": [
      1,
      22,
      43
    ]
  },
  {
    "seed": 69,
    "B": 3,
    "mc_idx": 43,
    "G": 0.20397663116455078,
    "A": 0.20249080657958984,
    "residual": 0.0014858245849609375,
    "schedule_steps": [
      34,
      47,
      60
    ]
  },
  {
    "seed": 69,
    "B": 3,
    "mc_idx": 44,
    "G": 0.1684889793395996,
    "A": 0.28610944747924805,
    "residual": -0.11762046813964844,
    "schedule_steps": [
      45,
      50,
      61
    ]
  },
  {
    "seed": 69,
    "B": 3,
    "mc_idx": 45,
    "G": 0.18303298950195312,
    "A": 0.15076446533203125,
    "residual": 0.032268524169921875,
    "schedule_steps": [
      41,
      47,
      60
    ]
  },
  {
    "seed": 69,
    "B": 3,
    "mc_idx": 46,
    "G": 0.27051830291748047,
    "A": 0.2920699119567871,
    "residual": -0.02155160903930664,
    "schedule_steps": [
      30,
      59,
      61
    ]
  },
  {
    "seed": 69,
    "B": 3,
    "mc_idx": 47,
    "G": 0.3392190933227539,
    "A": 0.2899026870727539,
    "residual": 0.04931640625,
    "schedule_steps": [
      15,
      18,
      55
    ]
  },
  {
    "seed": 69,
    "B": 3,
    "mc_idx": 48,
    "G": 0.20676136016845703,
    "A": 0.2303752899169922,
    "residual": -0.023613929748535156,
    "schedule_steps": [
      1,
      38,
      59
    ]
  },
  {
    "seed": 69,
    "B": 3,
    "mc_idx": 49,
    "G": 0.3673734664916992,
    "A": 0.2923274040222168,
    "residual": 0.07504606246948242,
    "schedule_steps": [
      27,
      41,
      57
    ]
  },
  {
    "seed": 69,
    "B": 3,
    "mc_idx": 50,
    "G": 0.2741842269897461,
    "A": 0.2708749771118164,
    "residual": 0.0033092498779296875,
    "schedule_steps": [
      40,
      42,
      61
    ]
  },
  {
    "seed": 69,
    "B": 3,
    "mc_idx": 51,
    "G": 0.8251581192016602,
    "A": 0.6009535789489746,
    "residual": 0.22420454025268555,
    "schedule_steps": [
      6,
      11,
      14
    ]
  },
  {
    "seed": 69,
    "B": 3,
    "mc_idx": 52,
    "G": 0.5262670516967773,
    "A": 0.7976465225219727,
    "residual": -0.2713794708251953,
    "schedule_steps": [
      3,
      7,
      39
    ]
  },
  {
    "seed": 69,
    "B": 3,
    "mc_idx": 53,
    "G": 0.06324338912963867,
    "A": 0.1998605728149414,
    "residual": -0.13661718368530273,
    "schedule_steps": [
      8,
      50,
      51
    ]
  },
  {
    "seed": 69,
    "B": 3,
    "mc_idx": 54,
    "G": 0.5021023750305176,
    "A": 0.43195056915283203,
    "residual": 0.07015180587768555,
    "schedule_steps": [
      6,
      18,
      55
    ]
  },
  {
    "seed": 69,
    "B": 3,
    "mc_idx": 55,
    "G": 0.20319795608520508,
    "A": 0.16450738906860352,
    "residual": 0.03869056701660156,
    "schedule_steps": [
      23,
      47,
      56
    ]
  },
  {
    "seed": 69,
    "B": 3,
    "mc_idx": 56,
    "G": 0.4340181350708008,
    "A": 0.5128417015075684,
    "residual": -0.07882356643676758,
    "schedule_steps": [
      4,
      46,
      54
    ]
  },
  {
    "seed": 69,
    "B": 3,
    "mc_idx": 57,
    "G": 0.4000253677368164,
    "A": 0.3158583641052246,
    "residual": 0.0841670036315918,
    "schedule_steps": [
      19,
      37,
      53
    ]
  },
  {
    "seed": 69,
    "B": 3,
    "mc_idx": 58,
    "G": 0.3560452461242676,
    "A": 0.13825273513793945,
    "residual": 0.21779251098632812,
    "schedule_steps": [
      3,
      32,
      47
    ]
  },
  {
    "seed": 69,
    "B": 3,
    "mc_idx": 59,
    "G": 0.32938289642333984,
    "A": 0.14263582229614258,
    "residual": 0.18674707412719727,
    "schedule_steps": [
      15,
      32,
      57
    ]
  },
  {
    "seed": 69,
    "B": 3,
    "mc_idx": 60,
    "G": 0.25322437286376953,
    "A": 0.13291311264038086,
    "residual": 0.12031126022338867,
    "schedule_steps": [
      14,
      15,
      32
    ]
  },
  {
    "seed": 69,
    "B": 3,
    "mc_idx": 61,
    "G": 0.2420501708984375,
    "A": 0.08834648132324219,
    "residual": 0.1537036895751953,
    "schedule_steps": [
      17,
      24,
      47
    ]
  },
  {
    "seed": 69,
    "B": 3,
    "mc_idx": 62,
    "G": 0.4577364921569824,
    "A": 0.25467872619628906,
    "residual": 0.20305776596069336,
    "schedule_steps": [
      6,
      20,
      57
    ]
  },
  {
    "seed": 69,
    "B": 3,
    "mc_idx": 63,
    "G": 0.14401674270629883,
    "A": 0.18296575546264648,
    "residual": -0.038949012756347656,
    "schedule_steps": [
      17,
      50,
      52
    ]
  },
  {
    "seed": 69,
    "B": 3,
    "mc_idx": 64,
    "G": 0.3934469223022461,
    "A": 0.397857666015625,
    "residual": -0.004410743713378906,
    "schedule_steps": [
      9,
      34,
      44
    ]
  },
  {
    "seed": 69,
    "B": 3,
    "mc_idx": 65,
    "G": 0.18769311904907227,
    "A": 0.17703533172607422,
    "residual": 0.010657787322998047,
    "schedule_steps": [
      10,
      30,
      47
    ]
  },
  {
    "seed": 69,
    "B": 3,
    "mc_idx": 66,
    "G": 0.17500019073486328,
    "A": 0.21938562393188477,
    "residual": -0.044385433197021484,
    "schedule_steps": [
      40,
      45,
      56
    ]
  },
  {
    "seed": 69,
    "B": 3,
    "mc_idx": 67,
    "G": 0.45650196075439453,
    "A": 0.7146735191345215,
    "residual": -0.25817155838012695,
    "schedule_steps": [
      7,
      27,
      34
    ]
  },
  {
    "seed": 69,
    "B": 3,
    "mc_idx": 68,
    "G": 0.3139491081237793,
    "A": 0.16928863525390625,
    "residual": 0.14466047286987305,
    "schedule_steps": [
      14,
      19,
      47
    ]
  },
  {
    "seed": 69,
    "B": 3,
    "mc_idx": 69,
    "G": 0.3343172073364258,
    "A": 0.47060728073120117,
    "residual": -0.1362900733947754,
    "schedule_steps": [
      34,
      41,
      58
    ]
  },
  {
    "seed": 69,
    "B": 3,
    "mc_idx": 70,
    "G": 0.7290239334106445,
    "A": 0.5534429550170898,
    "residual": 0.1755809783935547,
    "schedule_steps": [
      7,
      8,
      15
    ]
  },
  {
    "seed": 69,
    "B": 3,
    "mc_idx": 71,
    "G": 0.47922658920288086,
    "A": 0.4081716537475586,
    "residual": 0.07105493545532227,
    "schedule_steps": [
      6,
      35,
      41
    ]
  },
  {
    "seed": 69,
    "B": 3,
    "mc_idx": 72,
    "G": 0.44090843200683594,
    "A": 0.3063492774963379,
    "residual": 0.13455915451049805,
    "schedule_steps": [
      9,
      10,
      32
    ]
  },
  {
    "seed": 69,
    "B": 3,
    "mc_idx": 73,
    "G": 0.4842205047607422,
    "A": 0.2464594841003418,
    "residual": 0.2377610206604004,
    "schedule_steps": [
      2,
      8,
      24
    ]
  },
  {
    "seed": 69,
    "B": 3,
    "mc_idx": 74,
    "G": 0.25728940963745117,
    "A": 0.24693012237548828,
    "residual": 0.01035928726196289,
    "schedule_steps": [
      21,
      44,
      45
    ]
  },
  {
    "seed": 69,
    "B": 3,
    "mc_idx": 75,
    "G": -0.01706695556640625,
    "A": 0.2009868621826172,
    "residual": -0.21805381774902344,
    "schedule_steps": [
      0,
      18,
      46
    ]
  },
  {
    "seed": 69,
    "B": 3,
    "mc_idx": 76,
    "G": 0.13518190383911133,
    "A": 0.13447046279907227,
    "residual": 0.0007114410400390625,
    "schedule_steps": [
      20,
      40,
      54
    ]
  },
  {
    "seed": 69,
    "B": 3,
    "mc_idx": 77,
    "G": 0.3482656478881836,
    "A": 0.2530856132507324,
    "residual": 0.09518003463745117,
    "schedule_steps": [
      2,
      22,
      48
    ]
  },
  {
    "seed": 69,
    "B": 3,
    "mc_idx": 78,
    "G": 0.6942300796508789,
    "A": 0.5576233863830566,
    "residual": 0.13660669326782227,
    "schedule_steps": [
      3,
      11,
      29
    ]
  },
  {
    "seed": 69,
    "B": 3,
    "mc_idx": 79,
    "G": 0.5172791481018066,
    "A": 0.38368988037109375,
    "residual": 0.1335892677307129,
    "schedule_steps": [
      3,
      22,
      59
    ]
  },
  {
    "seed": 69,
    "B": 3,
    "mc_idx": 80,
    "G": 0.40337419509887695,
    "A": 0.5883049964904785,
    "residual": -0.18493080139160156,
    "schedule_steps": [
      4,
      46,
      58
    ]
  },
  {
    "seed": 69,
    "B": 3,
    "mc_idx": 81,
    "G": 0.1413893699645996,
    "A": 0.2640533447265625,
    "residual": -0.12266397476196289,
    "schedule_steps": [
      17,
      21,
      36
    ]
  },
  {
    "seed": 69,
    "B": 3,
    "mc_idx": 82,
    "G": 0.22266244888305664,
    "A": 0.26323366165161133,
    "residual": -0.04057121276855469,
    "schedule_steps": [
      8,
      19,
      26
    ]
  },
  {
    "seed": 69,
    "B": 3,
    "mc_idx": 83,
    "G": 0.3150310516357422,
    "A": 0.199127197265625,
    "residual": 0.11590385437011719,
    "schedule_steps": [
      14,
      22,
      53
    ]
  },
  {
    "seed": 69,
    "B": 3,
    "mc_idx": 84,
    "G": 0.32295751571655273,
    "A": 0.32158374786376953,
    "residual": 0.0013737678527832031,
    "schedule_steps": [
      27,
      34,
      51
    ]
  },
  {
    "seed": 69,
    "B": 3,
    "mc_idx": 85,
    "G": 0.10284090042114258,
    "A": 0.21262788772583008,
    "residual": -0.1097869873046875,
    "schedule_steps": [
      36,
      46,
      53
    ]
  },
  {
    "seed": 69,
    "B": 3,
    "mc_idx": 86,
    "G": 0.39916563034057617,
    "A": 0.3087496757507324,
    "residual": 0.09041595458984375,
    "schedule_steps": [
      9,
      37,
      44
    ]
  },
  {
    "seed": 69,
    "B": 3,
    "mc_idx": 87,
    "G": 0.3418412208557129,
    "A": 0.2694997787475586,
    "residual": 0.0723414421081543,
    "schedule_steps": [
      10,
      27,
      51
    ]
  },
  {
    "seed": 69,
    "B": 3,
    "mc_idx": 88,
    "G": 0.21814441680908203,
    "A": 0.3211688995361328,
    "residual": -0.10302448272705078,
    "schedule_steps": [
      21,
      36,
      45
    ]
  },
  {
    "seed": 69,
    "B": 3,
    "mc_idx": 89,
    "G": 0.33852434158325195,
    "A": 0.2744283676147461,
    "residual": 0.06409597396850586,
    "schedule_steps": [
      30,
      41,
      56
    ]
  },
  {
    "seed": 69,
    "B": 3,
    "mc_idx": 90,
    "G": 0.35489892959594727,
    "A": 0.19122743606567383,
    "residual": 0.16367149353027344,
    "schedule_steps": [
      26,
      45,
      54
    ]
  },
  {
    "seed": 69,
    "B": 3,
    "mc_idx": 91,
    "G": 0.18228721618652344,
    "A": 0.386538028717041,
    "residual": -0.20425081253051758,
    "schedule_steps": [
      38,
      39,
      61
    ]
  },
  {
    "seed": 69,
    "B": 3,
    "mc_idx": 92,
    "G": 0.2004237174987793,
    "A": 0.21102190017700195,
    "residual": -0.010598182678222656,
    "schedule_steps": [
      40,
      44,
      62
    ]
  },
  {
    "seed": 69,
    "B": 3,
    "mc_idx": 93,
    "G": 0.35430383682250977,
    "A": 0.4300498962402344,
    "residual": -0.07574605941772461,
    "schedule_steps": [
      1,
      11,
      50
    ]
  },
  {
    "seed": 69,
    "B": 3,
    "mc_idx": 94,
    "G": 0.26169681549072266,
    "A": 0.3270540237426758,
    "residual": -0.06535720825195312,
    "schedule_steps": [
      38,
      54,
      58
    ]
  },
  {
    "seed": 69,
    "B": 3,
    "mc_idx": 95,
    "G": 0.20466852188110352,
    "A": 0.36971330642700195,
    "residual": -0.16504478454589844,
    "schedule_steps": [
      37,
      43,
      49
    ]
  },
  {
    "seed": 69,
    "B": 3,
    "mc_idx": 96,
    "G": 0.46738767623901367,
    "A": 0.5804476737976074,
    "residual": -0.11305999755859375,
    "schedule_steps": [
      4,
      21,
      31
    ]
  },
  {
    "seed": 69,
    "B": 3,
    "mc_idx": 97,
    "G": 0.2056565284729004,
    "A": 0.3130321502685547,
    "residual": -0.1073756217956543,
    "schedule_steps": [
      40,
      50,
      61
    ]
  },
  {
    "seed": 69,
    "B": 3,
    "mc_idx": 98,
    "G": 0.5850629806518555,
    "A": 0.6263232231140137,
    "residual": -0.0412602424621582,
    "schedule_steps": [
      6,
      16,
      18
    ]
  },
  {
    "seed": 69,
    "B": 3,
    "mc_idx": 99,
    "G": 0.48548460006713867,
    "A": 0.4374661445617676,
    "residual": 0.048018455505371094,
    "schedule_steps": [
      3,
      10,
      48
    ]
  },
  {
    "seed": 69,
    "B": 4,
    "mc_idx": 0,
    "G": 0.5551948547363281,
    "A": 0.7754316329956055,
    "residual": -0.22023677825927734,
    "schedule_steps": [
      12,
      33,
      34,
      42
    ]
  },
  {
    "seed": 69,
    "B": 4,
    "mc_idx": 1,
    "G": 0.5056953430175781,
    "A": 0.384458065032959,
    "residual": 0.12123727798461914,
    "schedule_steps": [
      3,
      20,
      24,
      57
    ]
  },
  {
    "seed": 69,
    "B": 4,
    "mc_idx": 2,
    "G": 0.16116571426391602,
    "A": 0.19883203506469727,
    "residual": -0.03766632080078125,
    "schedule_steps": [
      20,
      26,
      27,
      50
    ]
  },
  {
    "seed": 69,
    "B": 4,
    "mc_idx": 3,
    "G": 0.3426513671875,
    "A": 0.3560009002685547,
    "residual": -0.013349533081054688,
    "schedule_steps": [
      24,
      37,
      44,
      57
    ]
  },
  {
    "seed": 69,
    "B": 4,
    "mc_idx": 4,
    "G": 0.13058185577392578,
    "A": 0.3301692008972168,
    "residual": -0.19958734512329102,
    "schedule_steps": [
      20,
      30,
      43,
      59
    ]
  },
  {
    "seed": 69,
    "B": 4,
    "mc_idx": 5,
    "G": 0.5563564300537109,
    "A": 0.6251091957092285,
    "residual": -0.06875276565551758,
    "schedule_steps": [
      12,
      56,
      58,
      63
    ]
  },
  {
    "seed": 69,
    "B": 4,
    "mc_idx": 6,
    "G": 0.4781174659729004,
    "A": 0.19780921936035156,
    "residual": 0.28030824661254883,
    "schedule_steps": [
      2,
      30,
      47,
      59
    ]
  },
  {
    "seed": 69,
    "B": 4,
    "mc_idx": 7,
    "G": 0.6425924301147461,
    "A": 0.682525634765625,
    "residual": -0.039933204650878906,
    "schedule_steps": [
      7,
      35,
      45,
      49
    ]
  },
  {
    "seed": 69,
    "B": 4,
    "mc_idx": 8,
    "G": 0.24088382720947266,
    "A": 0.27317285537719727,
    "residual": -0.03228902816772461,
    "schedule_steps": [
      0,
      41,
      42,
      50
    ]
  },
  {
    "seed": 69,
    "B": 4,
    "mc_idx": 9,
    "G": 0.46698951721191406,
    "A": 0.5214138031005859,
    "residual": -0.054424285888671875,
    "schedule_steps": [
      9,
      30,
      36,
      39
    ]
  },
  {
    "seed": 69,
    "B": 4,
    "mc_idx": 10,
    "G": 0.6946420669555664,
    "A": 0.6554651260375977,
    "residual": 0.03917694091796875,
    "schedule_steps": [
      2,
      12,
      15,
      37
    ]
  },
  {
    "seed": 69,
    "B": 4,
    "mc_idx": 11,
    "G": 0.4866819381713867,
    "A": 0.4476633071899414,
    "residual": 0.03901863098144531,
    "schedule_steps": [
      11,
      25,
      27,
      47
    ]
  },
  {
    "seed": 69,
    "B": 4,
    "mc_idx": 12,
    "G": 0.33835315704345703,
    "A": 0.44295406341552734,
    "residual": -0.10460090637207031,
    "schedule_steps": [
      23,
      39,
      52,
      53
    ]
  },
  {
    "seed": 69,
    "B": 4,
    "mc_idx": 13,
    "G": 0.37323808670043945,
    "A": 0.2680811882019043,
    "residual": 0.10515689849853516,
    "schedule_steps": [
      0,
      8,
      24,
      58
    ]
  },
  {
    "seed": 69,
    "B": 4,
    "mc_idx": 14,
    "G": 0.4578695297241211,
    "A": 0.8043122291564941,
    "residual": -0.34644269943237305,
    "schedule_steps": [
      4,
      34,
      37,
      61
    ]
  },
  {
    "seed": 69,
    "B": 4,
    "mc_idx": 15,
    "G": 0.3889002799987793,
    "A": 0.30686235427856445,
    "residual": 0.08203792572021484,
    "schedule_steps": [
      30,
      35,
      37,
      53
    ]
  },
  {
    "seed": 69,
    "B": 4,
    "mc_idx": 16,
    "G": 0.21149682998657227,
    "A": 0.2667117118835449,
    "residual": -0.055214881896972656,
    "schedule_steps": [
      8,
      13,
      21,
      29
    ]
  },
  {
    "seed": 69,
    "B": 4,
    "mc_idx": 17,
    "G": 0.2427372932434082,
    "A": 0.27251720428466797,
    "residual": -0.029779911041259766,
    "schedule_steps": [
      0,
      9,
      54,
      59
    ]
  },
  {
    "seed": 69,
    "B": 4,
    "mc_idx": 18,
    "G": 0.32308197021484375,
    "A": 0.3671555519104004,
    "residual": -0.04407358169555664,
    "schedule_steps": [
      16,
      20,
      42,
      49
    ]
  },
  {
    "seed": 69,
    "B": 4,
    "mc_idx": 19,
    "G": 0.9405961036682129,
    "A": 0.7024660110473633,
    "residual": 0.2381300926208496,
    "schedule_steps": [
      7,
      14,
      41,
      53
    ]
  },
  {
    "seed": 69,
    "B": 4,
    "mc_idx": 20,
    "G": 0.21127653121948242,
    "A": 0.33087635040283203,
    "residual": -0.11959981918334961,
    "schedule_steps": [
      21,
      48,
      62,
      63
    ]
  },
  {
    "seed": 69,
    "B": 4,
    "mc_idx": 21,
    "G": 0.6738452911376953,
    "A": 0.7386083602905273,
    "residual": -0.06476306915283203,
    "schedule_steps": [
      7,
      15,
      18,
      55
    ]
  },
  {
    "seed": 69,
    "B": 4,
    "mc_idx": 22,
    "G": 0.3279380798339844,
    "A": 0.4510021209716797,
    "residual": -0.12306404113769531,
    "schedule_steps": [
      16,
      17,
      33,
      57
    ]
  },
  {
    "seed": 69,
    "B": 4,
    "mc_idx": 23,
    "G": 0.09239721298217773,
    "A": 0.5188922882080078,
    "residual": -0.4264950752258301,
    "schedule_steps": [
      10,
      18,
      21,
      27
    ]
  },
  {
    "seed": 69,
    "B": 4,
    "mc_idx": 24,
    "G": 0.5596098899841309,
    "A": 0.7970190048217773,
    "residual": -0.23740911483764648,
    "schedule_steps": [
      8,
      12,
      23,
      41
    ]
  },
  {
    "seed": 69,
    "B": 4,
    "mc_idx": 25,
    "G": 0.2367420196533203,
    "A": 0.43242788314819336,
    "residual": -0.19568586349487305,
    "schedule_steps": [
      21,
      34,
      51,
      54
    ]
  },
  {
    "seed": 69,
    "B": 4,
    "mc_idx": 26,
    "G": 0.6651959419250488,
    "A": 0.3479886054992676,
    "residual": 0.31720733642578125,
    "schedule_steps": [
      6,
      20,
      24,
      44
    ]
  },
  {
    "seed": 69,
    "B": 4,
    "mc_idx": 27,
    "G": 0.3825411796569824,
    "A": 0.5015692710876465,
    "residual": -0.11902809143066406,
    "schedule_steps": [
      9,
      15,
      24,
      39
    ]
  },
  {
    "seed": 69,
    "B": 4,
    "mc_idx": 28,
    "G": 0.2715754508972168,
    "A": 0.2024059295654297,
    "residual": 0.06916952133178711,
    "schedule_steps": [
      0,
      29,
      33,
      50
    ]
  },
  {
    "seed": 69,
    "B": 4,
    "mc_idx": 29,
    "G": 0.28098154067993164,
    "A": 0.28609371185302734,
    "residual": -0.005112171173095703,
    "schedule_steps": [
      33,
      45,
      51,
      53
    ]
  },
  {
    "seed": 69,
    "B": 4,
    "mc_idx": 30,
    "G": 0.5917959213256836,
    "A": 0.5715904235839844,
    "residual": 0.02020549774169922,
    "schedule_steps": [
      12,
      35,
      52,
      55
    ]
  },
  {
    "seed": 69,
    "B": 4,
    "mc_idx": 31,
    "G": 0.13608407974243164,
    "A": 0.41922473907470703,
    "residual": -0.2831406593322754,
    "schedule_steps": [
      8,
      41,
      50,
      58
    ]
  },
  {
    "seed": 69,
    "B": 4,
    "mc_idx": 32,
    "G": 0.18930721282958984,
    "A": 0.2759413719177246,
    "residual": -0.08663415908813477,
    "schedule_steps": [
      5,
      48,
      49,
      55
    ]
  },
  {
    "seed": 69,
    "B": 4,
    "mc_idx": 33,
    "G": 0.6087017059326172,
    "A": 0.5256142616271973,
    "residual": 0.08308744430541992,
    "schedule_steps": [
      4,
      32,
      49,
      56
    ]
  },
  {
    "seed": 69,
    "B": 4,
    "mc_idx": 34,
    "G": 0.4001002311706543,
    "A": 0.3652205467224121,
    "residual": 0.03487968444824219,
    "schedule_steps": [
      26,
      33,
      35,
      39
    ]
  },
  {
    "seed": 69,
    "B": 4,
    "mc_idx": 35,
    "G": 0.6420469284057617,
    "A": 0.4444541931152344,
    "residual": 0.19759273529052734,
    "schedule_steps": [
      8,
      16,
      31,
      40
    ]
  },
  {
    "seed": 69,
    "B": 4,
    "mc_idx": 36,
    "G": 0.3321356773376465,
    "A": 0.2626338005065918,
    "residual": 0.06950187683105469,
    "schedule_steps": [
      20,
      22,
      23,
      28
    ]
  },
  {
    "seed": 69,
    "B": 4,
    "mc_idx": 37,
    "G": 0.23930883407592773,
    "A": 0.4210696220397949,
    "residual": -0.1817607879638672,
    "schedule_steps": [
      21,
      33,
      37,
      45
    ]
  },
  {
    "seed": 69,
    "B": 4,
    "mc_idx": 38,
    "G": 0.4848670959472656,
    "A": 0.17035484313964844,
    "residual": 0.3145122528076172,
    "schedule_steps": [
      2,
      5,
      17,
      29
    ]
  },
  {
    "seed": 69,
    "B": 4,
    "mc_idx": 39,
    "G": 0.6318850517272949,
    "A": 0.5585789680480957,
    "residual": 0.07330608367919922,
    "schedule_steps": [
      7,
      28,
      32,
      33
    ]
  },
  {
    "seed": 69,
    "B": 4,
    "mc_idx": 40,
    "G": 0.2851705551147461,
    "A": 0.4266681671142578,
    "residual": -0.14149761199951172,
    "schedule_steps": [
      34,
      52,
      60,
      61
    ]
  },
  {
    "seed": 69,
    "B": 4,
    "mc_idx": 41,
    "G": 0.27788877487182617,
    "A": 0.2496647834777832,
    "residual": 0.02822399139404297,
    "schedule_steps": [
      26,
      35,
      45,
      52
    ]
  },
  {
    "seed": 69,
    "B": 4,
    "mc_idx": 42,
    "G": 0.5145511627197266,
    "A": 0.4215688705444336,
    "residual": 0.09298229217529297,
    "schedule_steps": [
      3,
      9,
      31,
      32
    ]
  },
  {
    "seed": 69,
    "B": 4,
    "mc_idx": 43,
    "G": 0.5145931243896484,
    "A": 0.5296931266784668,
    "residual": -0.01510000228881836,
    "schedule_steps": [
      16,
      38,
      40,
      44
    ]
  },
  {
    "seed": 69,
    "B": 4,
    "mc_idx": 44,
    "G": 0.584925651550293,
    "A": 0.3529682159423828,
    "residual": 0.23195743560791016,
    "schedule_steps": [
      2,
      13,
      50,
      61
    ]
  },
  {
    "seed": 69,
    "B": 4,
    "mc_idx": 45,
    "G": 0.37995290756225586,
    "A": 0.16289138793945312,
    "residual": 0.21706151962280273,
    "schedule_steps": [
      8,
      32,
      35,
      62
    ]
  },
  {
    "seed": 69,
    "B": 4,
    "mc_idx": 46,
    "G": 0.3187227249145508,
    "A": 0.40262603759765625,
    "residual": -0.08390331268310547,
    "schedule_steps": [
      3,
      56,
      57,
      59
    ]
  },
  {
    "seed": 69,
    "B": 4,
    "mc_idx": 47,
    "G": 0.24707984924316406,
    "A": 0.3948535919189453,
    "residual": -0.14777374267578125,
    "schedule_steps": [
      10,
      31,
      41,
      63
    ]
  },
  {
    "seed": 69,
    "B": 4,
    "mc_idx": 48,
    "G": 0.6107711791992188,
    "A": 0.7019968032836914,
    "residual": -0.09122562408447266,
    "schedule_steps": [
      12,
      28,
      34,
      49
    ]
  },
  {
    "seed": 69,
    "B": 4,
    "mc_idx": 49,
    "G": 0.6497373580932617,
    "A": 0.46230363845825195,
    "residual": 0.18743371963500977,
    "schedule_steps": [
      11,
      17,
      35,
      63
    ]
  },
  {
    "seed": 69,
    "B": 4,
    "mc_idx": 50,
    "G": 0.2501640319824219,
    "A": 0.44832420349121094,
    "residual": -0.19816017150878906,
    "schedule_steps": [
      13,
      19,
      22,
      25
    ]
  },
  {
    "seed": 69,
    "B": 4,
    "mc_idx": 51,
    "G": 0.6240630149841309,
    "A": 0.23847150802612305,
    "residual": 0.3855915069580078,
    "schedule_steps": [
      2,
      20,
      38,
      63
    ]
  },
  {
    "seed": 69,
    "B": 4,
    "mc_idx": 52,
    "G": 0.35478878021240234,
    "A": 1.1549158096313477,
    "residual": -0.8001270294189453,
    "schedule_steps": [
      6,
      7,
      12,
      48
    ]
  },
  {
    "seed": 69,
    "B": 4,
    "mc_idx": 53,
    "G": 0.5472593307495117,
    "A": 0.44766902923583984,
    "residual": 0.09959030151367188,
    "schedule_steps": [
      15,
      18,
      36,
      59
    ]
  },
  {
    "seed": 69,
    "B": 4,
    "mc_idx": 54,
    "G": 0.6030664443969727,
    "A": 0.5401115417480469,
    "residual": 0.06295490264892578,
    "schedule_steps": [
      3,
      23,
      44,
      49
    ]
  },
  {
    "seed": 69,
    "B": 4,
    "mc_idx": 55,
    "G": 0.3435091972351074,
    "A": 0.42563390731811523,
    "residual": -0.08212471008300781,
    "schedule_steps": [
      18,
      41,
      52,
      55
    ]
  },
  {
    "seed": 69,
    "B": 4,
    "mc_idx": 56,
    "G": 0.2109537124633789,
    "A": 0.2928128242492676,
    "residual": -0.08185911178588867,
    "schedule_steps": [
      5,
      51,
      59,
      61
    ]
  },
  {
    "seed": 69,
    "B": 4,
    "mc_idx": 57,
    "G": 0.46460485458374023,
    "A": 0.27216672897338867,
    "residual": 0.19243812561035156,
    "schedule_steps": [
      31,
      37,
      45,
      56
    ]
  },
  {
    "seed": 69,
    "B": 4,
    "mc_idx": 58,
    "G": 0.2531437873840332,
    "A": 0.3543062210083008,
    "residual": -0.10116243362426758,
    "schedule_steps": [
      29,
      34,
      35,
      60
    ]
  },
  {
    "seed": 69,
    "B": 4,
    "mc_idx": 59,
    "G": 0.22254180908203125,
    "A": 0.3525848388671875,
    "residual": -0.13004302978515625,
    "schedule_steps": [
      5,
      30,
      41,
      62
    ]
  },
  {
    "seed": 69,
    "B": 4,
    "mc_idx": 60,
    "G": 0.20112085342407227,
    "A": 0.288968563079834,
    "residual": -0.08784770965576172,
    "schedule_steps": [
      37,
      52,
      60,
      63
    ]
  },
  {
    "seed": 69,
    "B": 4,
    "mc_idx": 61,
    "G": 0.6482295989990234,
    "A": 0.628532886505127,
    "residual": 0.019696712493896484,
    "schedule_steps": [
      12,
      29,
      39,
      55
    ]
  },
  {
    "seed": 69,
    "B": 4,
    "mc_idx": 62,
    "G": 0.11405754089355469,
    "A": 0.347257137298584,
    "residual": -0.2331995964050293,
    "schedule_steps": [
      0,
      11,
      28,
      31
    ]
  },
  {
    "seed": 69,
    "B": 4,
    "mc_idx": 63,
    "G": 0.2246394157409668,
    "A": 0.2172989845275879,
    "residual": 0.007340431213378906,
    "schedule_steps": [
      15,
      17,
      22,
      44
    ]
  },
  {
    "seed": 69,
    "B": 4,
    "mc_idx": 64,
    "G": 0.46954917907714844,
    "A": 0.34610462188720703,
    "residual": 0.1234445571899414,
    "schedule_steps": [
      9,
      31,
      44,
      48
    ]
  },
  {
    "seed": 69,
    "B": 4,
    "mc_idx": 65,
    "G": 0.08682394027709961,
    "A": 0.2611727714538574,
    "residual": -0.1743488311767578,
    "schedule_steps": [
      5,
      26,
      56,
      58
    ]
  },
  {
    "seed": 69,
    "B": 4,
    "mc_idx": 66,
    "G": 0.2874107360839844,
    "A": 0.3683013916015625,
    "residual": -0.08089065551757812,
    "schedule_steps": [
      31,
      36,
      41,
      52
    ]
  },
  {
    "seed": 69,
    "B": 4,
    "mc_idx": 67,
    "G": 0.2464580535888672,
    "A": 0.38048410415649414,
    "residual": -0.13402605056762695,
    "schedule_steps": [
      10,
      29,
      43,
      53
    ]
  },
  {
    "seed": 69,
    "B": 4,
    "mc_idx": 68,
    "G": 0.19896554946899414,
    "A": 0.24977970123291016,
    "residual": -0.050814151763916016,
    "schedule_steps": [
      17,
      49,
      53,
      59
    ]
  },
  {
    "seed": 69,
    "B": 4,
    "mc_idx": 69,
    "G": 0.42821311950683594,
    "A": 0.6451573371887207,
    "residual": -0.21694421768188477,
    "schedule_steps": [
      2,
      12,
      46,
      50
    ]
  },
  {
    "seed": 69,
    "B": 4,
    "mc_idx": 70,
    "G": 0.3669719696044922,
    "A": 0.33118438720703125,
    "residual": 0.03578758239746094,
    "schedule_steps": [
      17,
      24,
      25,
      35
    ]
  },
  {
    "seed": 69,
    "B": 4,
    "mc_idx": 71,
    "G": 0.35795164108276367,
    "A": 0.4163947105407715,
    "residual": -0.05844306945800781,
    "schedule_steps": [
      14,
      17,
      18,
      39
    ]
  },
  {
    "seed": 69,
    "B": 4,
    "mc_idx": 72,
    "G": 0.9201221466064453,
    "A": 0.8181943893432617,
    "residual": 0.1019277572631836,
    "schedule_steps": [
      4,
      12,
      13,
      47
    ]
  },
  {
    "seed": 69,
    "B": 4,
    "mc_idx": 73,
    "G": 0.1846938133239746,
    "A": 0.3564333915710449,
    "residual": -0.1717395782470703,
    "schedule_steps": [
      5,
      10,
      22,
      57
    ]
  },
  {
    "seed": 69,
    "B": 4,
    "mc_idx": 74,
    "G": 0.28296661376953125,
    "A": 0.3207268714904785,
    "residual": -0.037760257720947266,
    "schedule_steps": [
      37,
      41,
      44,
      56
    ]
  },
  {
    "seed": 69,
    "B": 4,
    "mc_idx": 75,
    "G": 0.4876880645751953,
    "A": 0.4053153991699219,
    "residual": 0.08237266540527344,
    "schedule_steps": [
      6,
      17,
      60,
      61
    ]
  },
  {
    "seed": 69,
    "B": 4,
    "mc_idx": 76,
    "G": 0.6611814498901367,
    "A": 0.6081576347351074,
    "residual": 0.0530238151550293,
    "schedule_steps": [
      4,
      26,
      37,
      55
    ]
  },
  {
    "seed": 69,
    "B": 4,
    "mc_idx": 77,
    "G": 0.4214162826538086,
    "A": 0.6278076171875,
    "residual": -0.2063913345336914,
    "schedule_steps": [
      0,
      4,
      23,
      42
    ]
  },
  {
    "seed": 69,
    "B": 4,
    "mc_idx": 78,
    "G": 0.2577342987060547,
    "A": 0.49257564544677734,
    "residual": -0.23484134674072266,
    "schedule_steps": [
      16,
      21,
      27,
      51
    ]
  },
  {
    "seed": 69,
    "B": 4,
    "mc_idx": 79,
    "G": 0.5131587982177734,
    "A": 0.7096896171569824,
    "residual": -0.19653081893920898,
    "schedule_steps": [
      9,
      12,
      45,
      52
    ]
  },
  {
    "seed": 69,
    "B": 4,
    "mc_idx": 80,
    "G": 0.40348386764526367,
    "A": 0.3226919174194336,
    "residual": 0.08079195022583008,
    "schedule_steps": [
      19,
      20,
      41,
      44
    ]
  },
  {
    "seed": 69,
    "B": 4,
    "mc_idx": 81,
    "G": 0.4478611946105957,
    "A": 0.5091409683227539,
    "residual": -0.0612797737121582,
    "schedule_steps": [
      11,
      49,
      53,
      55
    ]
  },
  {
    "seed": 69,
    "B": 4,
    "mc_idx": 82,
    "G": 0.6357955932617188,
    "A": 0.647005558013916,
    "residual": -0.011209964752197266,
    "schedule_steps": [
      6,
      34,
      41,
      61
    ]
  },
  {
    "seed": 69,
    "B": 4,
    "mc_idx": 83,
    "G": 0.41140222549438477,
    "A": 0.23764896392822266,
    "residual": 0.1737532615661621,
    "schedule_steps": [
      15,
      25,
      32,
      52
    ]
  },
  {
    "seed": 69,
    "B": 4,
    "mc_idx": 84,
    "G": 0.26453590393066406,
    "A": 0.31518983840942383,
    "residual": -0.050653934478759766,
    "schedule_steps": [
      29,
      31,
      50,
      58
    ]
  },
  {
    "seed": 69,
    "B": 4,
    "mc_idx": 85,
    "G": 0.8562684059143066,
    "A": 0.7908420562744141,
    "residual": 0.06542634963989258,
    "schedule_steps": [
      6,
      11,
      22,
      43
    ]
  },
  {
    "seed": 69,
    "B": 4,
    "mc_idx": 86,
    "G": 0.2557106018066406,
    "A": 0.24408340454101562,
    "residual": 0.011627197265625,
    "schedule_steps": [
      1,
      24,
      26,
      35
    ]
  },
  {
    "seed": 69,
    "B": 4,
    "mc_idx": 87,
    "G": 0.36929893493652344,
    "A": 0.28232908248901367,
    "residual": 0.08696985244750977,
    "schedule_steps": [
      31,
      44,
      46,
      58
    ]
  },
  {
    "seed": 69,
    "B": 4,
    "mc_idx": 88,
    "G": 0.42302751541137695,
    "A": 0.29102611541748047,
    "residual": 0.13200139999389648,
    "schedule_steps": [
      2,
      5,
      45,
      59
    ]
  },
  {
    "seed": 69,
    "B": 4,
    "mc_idx": 89,
    "G": 0.3976101875305176,
    "A": 0.1897420883178711,
    "residual": 0.20786809921264648,
    "schedule_steps": [
      1,
      15,
      27,
      51
    ]
  },
  {
    "seed": 69,
    "B": 4,
    "mc_idx": 90,
    "G": 0.6757240295410156,
    "A": 0.4393301010131836,
    "residual": 0.23639392852783203,
    "schedule_steps": [
      2,
      14,
      16,
      54
    ]
  },
  {
    "seed": 69,
    "B": 4,
    "mc_idx": 91,
    "G": 0.25379276275634766,
    "A": 0.22448253631591797,
    "residual": 0.029310226440429688,
    "schedule_steps": [
      1,
      26,
      36,
      51
    ]
  },
  {
    "seed": 69,
    "B": 4,
    "mc_idx": 92,
    "G": 0.10267066955566406,
    "A": 0.1070857048034668,
    "residual": -0.004415035247802734,
    "schedule_steps": [
      24,
      28,
      47,
      53
    ]
  },
  {
    "seed": 69,
    "B": 4,
    "mc_idx": 93,
    "G": 0.41227006912231445,
    "A": 0.9855647087097168,
    "residual": -0.5732946395874023,
    "schedule_steps": [
      6,
      7,
      9,
      43
    ]
  },
  {
    "seed": 69,
    "B": 4,
    "mc_idx": 94,
    "G": 0.25708866119384766,
    "A": 0.35668468475341797,
    "residual": -0.09959602355957031,
    "schedule_steps": [
      10,
      22,
      42,
      62
    ]
  },
  {
    "seed": 69,
    "B": 4,
    "mc_idx": 95,
    "G": 0.4535541534423828,
    "A": 0.3202481269836426,
    "residual": 0.13330602645874023,
    "schedule_steps": [
      17,
      18,
      42,
      51
    ]
  },
  {
    "seed": 69,
    "B": 4,
    "mc_idx": 96,
    "G": 0.2446422576904297,
    "A": 0.3914055824279785,
    "residual": -0.14676332473754883,
    "schedule_steps": [
      31,
      36,
      39,
      57
    ]
  },
  {
    "seed": 69,
    "B": 4,
    "mc_idx": 97,
    "G": 0.323610782623291,
    "A": 0.22109508514404297,
    "residual": 0.10251569747924805,
    "schedule_steps": [
      22,
      28,
      30,
      56
    ]
  },
  {
    "seed": 69,
    "B": 4,
    "mc_idx": 98,
    "G": 0.7143383026123047,
    "A": 0.19957971572875977,
    "residual": 0.5147585868835449,
    "schedule_steps": [
      2,
      14,
      28,
      51
    ]
  },
  {
    "seed": 69,
    "B": 4,
    "mc_idx": 99,
    "G": 0.3499908447265625,
    "A": 0.5829496383666992,
    "residual": -0.23295879364013672,
    "schedule_steps": [
      8,
      12,
      57,
      63
    ]
  }
]