[
  {
    "seed": 71,
    "B": 2,
    "policy": "uniform",
    "signal_kind": "none",
    "signal_name": null,
    "allocation_policy": "uniform",
    "G": 0.254150390625,
    "A": 0.18641996383666992,
    "residual": 0.06773042678833008,
    "f_base": -4.862257957458496,
    "f_schedule": -4.608107566833496,
    "schedule_steps": [
      0,
      32
    ],
    "budget": 2,
    "wall_time": 12.724627017974854
  },
  {
    "seed": 71,
    "B": 2,
    "policy": "front",
    "signal_kind": "none",
    "signal_name": null,
    "allocation_policy": "front",
    "G": -0.06501102447509766,
    "A": -0.36984872817993164,
    "residual": 0.304837703704834,
    "f_base": -4.862257957458496,
    "f_schedule": -4.927268981933594,
    "schedule_steps": [
      0,
      1
    ],
    "budget": 2,
    "wall_time": 12.726054668426514
  },
  {
    "seed": 71,
    "B": 2,
    "policy": "back",
    "signal_kind": "none",
    "signal_name": null,
    "allocation_policy": "back",
    "G": 0.11909246444702148,
    "A": 0.18727493286132812,
    "residual": -0.06818246841430664,
    "f_base": -4.862257957458496,
    "f_schedule": -4.743165493011475,
    "schedule_steps": [
      62,
      63
    ],
    "budget": 2,
    "wall_time": 12.725629568099976
  },
  {
    "seed": 71,
    "B": 2,
    "policy": "middle",
    "signal_kind": "none",
    "signal_name": null,
    "allocation_policy": "middle",
    "G": 0.05614948272705078,
    "A": 0.2962479591369629,
    "residual": -0.2400984764099121,
    "f_base": -4.862257957458496,
    "f_schedule": -4.806108474731445,
    "schedule_steps": [
      31,
      32
    ],
    "budget": 2,
    "wall_time": 12.727264881134033
  },
  {
    "seed": 71,
    "B": 2,
    "policy": "entropy_top_B_pt",
    "signal_kind": "per_trajectory_signal",
    "signal_name": "entropy",
    "allocation_policy": "top_B",
    "G": -0.06501102447509766,
    "A": -0.36984872817993164,
    "residual": 0.304837703704834,
    "f_base": -4.862257957458496,
    "f_schedule": -4.927268981933594,
    "schedule_steps": [
      0,
      1
    ],
    "budget": 2,
    "wall_time": 12.723876476287842
  },
  {
    "seed": 71,
    "B": 2,
    "policy": "entropy_bot_B_pt",
    "signal_kind": "per_trajectory_signal",
    "signal_name": "entropy",
    "allocation_policy": "bottom_B",
    "G": 0.21739912033081055,
    "A": 0.22980213165283203,
    "residual": -0.012403011322021484,
    "f_base": -4.862257957458496,
    "f_schedule": -4.6448588371276855,
    "schedule_steps": [
      42,
      54
    ],
    "budget": 2,
    "wall_time": 12.72593903541565
  },
  {
    "seed": 71,
    "B": 2,
    "policy": "margin_top_B_pt",
    "signal_kind": "per_trajectory_signal",
    "signal_name": "inverse_margin",
    "allocation_policy": "top_B",
    "G": -0.06501102447509766,
    "A": -0.36984872817993164,
    "residual": 0.304837703704834,
    "f_base": -4.862257957458496,
    "f_schedule": -4.927268981933594,
    "schedule_steps": [
      0,
      1
    ],
    "budget": 2,
    "wall_time": 12.727397918701172
  },
  {
    "seed": 71,
    "B": 2,
    "policy": "quality_top_B_pt",
    "signal_kind": "per_trajectory_signal",
    "signal_name": "quality_mass_proxy",
    "allocation_policy": "top_B",
    "G": -0.06501102447509766,
    "A": -0.36984872817993164,
    "residual": 0.304837703704834,
    "f_base": -4.862257957458496,
    "f_schedule": -4.927268981933594,
    "schedule_steps": [
      0,
      1
    ],
    "budget": 2,
    "wall_time": 12.726996660232544
  },
  {
    "seed": 71,
    "B": 2,
    "policy": "entropy_top_B_mp",
    "signal_kind": "mean_profile_signal",
    "signal_name": "entropy",
    "allocation_policy": "top_B",
    "G": -0.06501102447509766,
    "A": -0.36984872817993164,
    "residual": 0.304837703704834,
    "f_base": -4.862257957458496,
    "f_schedule": -4.927268981933594,
    "schedule_steps": [
      0,
      1
    ],
    "budget": 2,
    "wall_time": 12.726771593093872
  },
  {
    "seed": 71,
    "B": 2,
    "policy": "mean_delta_oracle",
    "signal_kind": "mean_delta",
    "signal_name": null,
    "allocation_policy": "top_B",
    "G": 0.3229527473449707,
    "A": 0.41281747817993164,
    "residual": -0.08986473083496094,
    "f_base": -4.862257957458496,
    "f_schedule": -4.539305210113525,
    "schedule_steps": [
      11,
      23
    ],
    "budget": 2,
    "wall_time": 12.732004880905151
  },
  {
    "seed": 71,
    "B": 3,
    "policy": "uniform",
    "signal_kind": "none",
    "signal_name": null,
    "allocation_policy": "uniform",
    "G": 0.5098328590393066,
    "A": 0.2535562515258789,
    "residual": 0.25627660751342773,
    "f_base": -4.862257957458496,
    "f_schedule": -4.3524250984191895,
    "schedule_steps": [
      0,
      21,
      42
    ],
    "budget": 3,
    "wall_time": 12.820913553237915
  },
  {
    "seed": 71,
    "B": 3,
    "policy": "front",
    "signal_kind": "none",
    "signal_name": null,
    "allocation_policy": "front",
    "G": -0.02352285385131836,
    "A": -0.36984872817993164,
    "residual": 0.3463258743286133,
    "f_base": -4.862257957458496,
    "f_schedule": -4.8857808113098145,
    "schedule_steps": [
      0,
      1,
      2
    ],
    "budget": 3,
    "wall_time": 12.861917972564697
  },
  {
    "seed": 71,
    "B": 3,
    "policy": "back",
    "signal_kind": "none",
    "signal_name": null,
    "allocation_policy": "back",
    "G": 0.13427019119262695,
    "A": 0.2885112762451172,
    "residual": -0.15424108505249023,
    "f_base": -4.862257957458496,
    "f_schedule": -4.727987766265869,
    "schedule_steps": [
      61,
      62,
      63
    ],
    "budget": 3,
    "wall_time": 12.84035587310791
  },
  {
    "seed": 71,
    "B": 3,
    "policy": "middle",
    "signal_kind": "none",
    "signal_name": null,
    "allocation_policy": "middle",
    "G": 0.20144128799438477,
    "A": 0.5331530570983887,
    "residual": -0.3317117691040039,
    "f_base": -4.862257957458496,
    "f_schedule": -4.660816669464111,
    "schedule_steps": [
      31,
      32,
      33
    ],
    "budget": 3,
    "wall_time": 12.846556186676025
  },
  {
    "seed": 71,
    "B": 3,
    "policy": "entropy_top_B_pt",
    "signal_kind": "per_trajectory_signal",
    "signal_name": "entropy",
    "allocation_policy": "top_B",
    "G": -0.02352285385131836,
    "A": -0.36984872817993164,
    "residual": 0.3463258743286133,
    "f_base": -4.862257957458496,
    "f_schedule": -4.8857808113098145,
    "schedule_steps": [
      0,
      1,
      2
    ],
    "budget": 3,
    "wall_time": 12.821904420852661
  },
  {
    "seed": 71,
    "B": 3,
    "policy": "entropy_bot_B_pt",
    "signal_kind": "per_trajectory_signal",
    "signal_name": "entropy",
    "allocation_policy": "bottom_B",
    "G": 0.3543825149536133,
    "A": 0.27178192138671875,
    "residual": 0.08260059356689453,
    "f_base": -4.862257957458496,
    "f_schedule": -4.507875442504883,
    "schedule_steps": [
      42,
      52,
      54
    ],
    "budget": 3,
    "wall_time": 12.823921203613281
  },
  {
    "seed": 71,
    "B": 3,
    "policy": "margin_top_B_pt",
    "signal_kind": "per_trajectory_signal",
    "signal_name": "inverse_margin",
    "allocation_policy": "top_B",
    "G": -0.02352285385131836,
    "A": -0.36984872817993164,
    "residual": 0.3463258743286133,
    "f_base": -4.862257957458496,
    "f_schedule": -4.8857808113098145,
    "schedule_steps": [
      0,
      1,
      2
    ],
    "budget": 3,
    "wall_time": 12.81910490989685
  },
  {
    "seed": 71,
    "B": 3,
    "policy": "quality_top_B_pt",
    "signal_kind": "per_trajectory_signal",
    "signal_name": "quality_mass_proxy",
    "allocation_policy": "top_B",
    "G": -0.02352285385131836,
    "A": -0.36984872817993164,
    "residual": 0.3463258743286133,
    "f_base": -4.862257957458496,
    "f_schedule": -4.8857808113098145,
    "schedule_steps": [
      0,
      1,
      2
    ],
    "budget": 3,
    "wall_time": 12.819936752319336
  },
  {
    "seed": 71,
    "B": 3,
    "policy": "entropy_top_B_mp",
    "signal_kind": "mean_profile_signal",
    "signal_name": "entropy",
    "allocation_policy": "top_B",
    "G": -0.02352285385131836,
    "A": -0.36984872817993164,
    "residual": 0.3463258743286133,
    "f_base": -4.862257957458496,
    "f_schedule": -4.8857808113098145,
    "schedule_steps": [
      0,
      1,
      2
    ],
    "budget": 3,
    "wall_time": 12.820361614227295
  },
  {
    "seed": 71,
    "B": 3,
    "policy": "mean_delta_oracle",
    "signal_kind": "mean_delta",
    "signal_name": null,
    "allocation_policy": "top_B",
    "G": 0.2597017288208008,
    "A": 0.5743393898010254,
    "residual": -0.3146376609802246,
    "f_base": -4.862257957458496,
    "f_schedule": -4.602556228637695,
    "schedule_steps": [
      11,
      23,
      29
    ],
    "budget": 3,
    "wall_time": 12.818644046783447
  },
  {
    "seed": 71,
    "B": 4,
    "policy": "uniform",
    "signal_kind": "none",
    "signal_name": null,
    "allocation_policy": "uniform",
    "G": 0.5559492111206055,
    "A": 0.1287851333618164,
    "residual": 0.42716407775878906,
    "f_base": -4.862257957458496,
    "f_schedule": -4.306308746337891,
    "schedule_steps": [
      0,
      16,
      32,
      48
    ],
    "budget": 4,
    "wall_time": 12.914201736450195
  },
  {
    "seed": 71,
    "B": 4,
    "policy": "front",
    "signal_kind": "none",
    "signal_name": null,
    "allocation_policy": "front",
    "G": 0.209503173828125,
    "A": -0.36984872817993164,
    "residual": 0.5793519020080566,
    "f_base": -4.862257957458496,
    "f_schedule": -4.652754783630371,
    "schedule_steps": [
      0,
      1,
      2,
      3
    ],
    "budget": 4,
    "wall_time": 12.912454605102539
  },
  {
    "seed": 71,
    "B": 4,
    "policy": "back",
    "signal_kind": "none",
    "signal_name": null,
    "allocation_policy": "back",
    "G": 0.1483011245727539,
    "A": 0.38974761962890625,
    "residual": -0.24144649505615234,
    "f_base": -4.862257957458496,
    "f_schedule": -4.713956832885742,
    "schedule_steps": [
      60,
      61,
      62,
      63
    ],
    "budget": 4,
    "wall_time": 12.919834852218628
  },
  {
    "seed": 71,
    "B": 4,
    "policy": "middle",
    "signal_kind": "none",
    "signal_name": null,
    "allocation_policy": "middle",
    "G": 0.4067258834838867,
    "A": 0.7712478637695312,
    "residual": -0.36452198028564453,
    "f_base": -4.862257957458496,
    "f_schedule": -4.455532073974609,
    "schedule_steps": [
      30,
      31,
      32,
      33
    ],
    "budget": 4,
    "wall_time": 12.917885303497314
  },
  {
    "seed": 71,
    "B": 4,
    "policy": "entropy_top_B_pt",
    "signal_kind": "per_trajectory_signal",
    "signal_name": "entropy",
    "allocation_policy": "top_B",
    "G": 0.209503173828125,
    "A": -0.36984872817993164,
    "residual": 0.5793519020080566,
    "f_base": -4.862257957458496,
    "f_schedule": -4.652754783630371,
    "schedule_steps": [
      0,
      1,
      2,
      3
    ],
    "budget": 4,
    "wall_time": 12.91783094406128
  },
  {
    "seed": 71,
    "B": 4,
    "policy": "entropy_bot_B_pt",
    "signal_kind": "per_trajectory_signal",
    "signal_name": "entropy",
    "allocation_policy": "bottom_B",
    "G": 0.37511110305786133,
    "A": 0.3080615997314453,
    "residual": 0.06704950332641602,
    "f_base": -4.862257957458496,
    "f_schedule": -4.487146854400635,
    "schedule_steps": [
      42,
      50,
      52,
      54
    ],
    "budget": 4,
    "wall_time": 12.920439720153809
  },
  {
    "seed": 71,
    "B": 4,
    "policy": "margin_top_B_pt",
    "signal_kind": "per_trajectory_signal",
    "signal_name": "inverse_margin",
    "allocation_policy": "top_B",
    "G": 0.209503173828125,
    "A": -0.36984872817993164,
    "residual": 0.5793519020080566,
    "f_base": -4.862257957458496,
    "f_schedule": -4.652754783630371,
    "schedule_steps": [
      0,
      1,
      2,
      3
    ],
    "budget": 4,
    "wall_time": 12.91809606552124
  },
  {
    "seed": 71,
    "B": 4,
    "policy": "quality_top_B_pt",
    "signal_kind": "per_trajectory_signal",
    "signal_name": "quality_mass_proxy",
    "allocation_policy": "top_B",
    "G": 0.209503173828125,
    "A": -0.36984872817993164,
    "residual": 0.5793519020080566,
    "f_base": -4.862257957458496,
    "f_schedule": -4.652754783630371,
    "schedule_steps": [
      0,
      1,
      2,
      3
    ],
    "budget": 4,
    "wall_time": 12.921514511108398
  },
  {
    "seed": 71,
    "B": 4,
    "policy": "entropy_top_B_mp",
    "signal_kind": "mean_profile_signal",
    "signal_name": "entropy",
    "allocation_policy": "top_B",
    "G": 0.209503173828125,
    "A": -0.36984872817993164,
    "residual": 0.5793519020080566,
    "f_base": -4.862257957458496,
    "f_schedule": -4.652754783630371,
    "schedule_steps": [
      0,
      1,
      2,
      3
    ],
    "budget": 4,
    "wall_time": 12.91913390159607
  },
  {
    "seed": 71,
    "B": 4,
    "policy": "mean_delta_oracle",
    "signal_kind": "mean_delta",
    "signal_name": null,
    "allocation_policy": "top_B",
    "G": 0.4746670722961426,
    "A": 0.6132221221923828,
    "residual": -0.13855504989624023,
    "f_base": -4.862257957458496,
    "f_schedule": -4.3875908851623535,
    "schedule_steps": [
      11,
      23,
      28,
      29
    ],
    "budget": 4,
    "wall_time": 12.918794393539429
  },
  {
    "seed": 71,
    "B": 8,
    "policy": "uniform",
    "signal_kind": "none",
    "signal_name": null,
    "allocation_policy": "uniform",
    "G": 0.5530548095703125,
    "A": 0.4663820266723633,
    "residual": 0.08667278289794922,
    "f_base": -4.862257957458496,
    "f_schedule": -4.309203147888184,
    "schedule_steps": [
      0,
      8,
      16,
      24,
      32,
      40,
      48,
      56
    ],
    "budget": 8,
    "wall_time": 13.294500827789307
  },
  {
    "seed": 71,
    "B": 8,
    "policy": "front",
    "signal_kind": "none",
    "signal_name": null,
    "allocation_policy": "front",
    "G": 0.10511159896850586,
    "A": -0.4525008201599121,
    "residual": 0.557612419128418,
    "f_base": -4.862257957458496,
    "f_schedule": -4.75714635848999,
    "schedule_steps": [
      0,
      1,
      2,
      3,
      4,
      5,
      6,
      7
    ],
    "budget": 8,
    "wall_time": 13.29465389251709
  },
  {
    "seed": 71,
    "B": 8,
    "policy": "back",
    "signal_kind": "none",
    "signal_name": null,
    "allocation_policy": "back",
    "G": 0.1978139877319336,
    "A": 0.6605224609375,
    "residual": -0.4627084732055664,
    "f_base": -4.862257957458496,
    "f_schedule": -4.6644439697265625,
    "schedule_steps": [
      56,
      57,
      58,
      59,
      60,
      61,
      62,
      63
    ],
    "budget": 8,
    "wall_time": 13.295409679412842
  },
  {
    "seed": 71,
    "B": 8,
    "policy": "middle",
    "signal_kind": "none",
    "signal_name": null,
    "allocation_policy": "middle",
    "G": 0.46773862838745117,
    "A": 1.2647037506103516,
    "residual": -0.7969651222229004,
    "f_base": -4.862257957458496,
    "f_schedule": -4.394519329071045,
    "schedule_steps": [
      28,
      29,
      30,
      31,
      32,
      33,
      34,
      35
    ],
    "budget": 8,
    "wall_time": 13.295561075210571
  },
  {
    "seed": 71,
    "B": 8,
    "policy": "entropy_top_B_pt",
    "signal_kind": "per_trajectory_signal",
    "signal_name": "entropy",
    "allocation_policy": "top_B",
    "G": -0.19441795349121094,
    "A": 0.1942882537841797,
    "residual": -0.3887062072753906,
    "f_base": -4.862257957458496,
    "f_schedule": -5.056675910949707,
    "schedule_steps": [
      0,
      1,
      2,
      3,
      4,
      5,
      6,
      9
    ],
    "budget": 8,
    "wall_time": 13.295289993286133
  },
  {
    "seed": 71,
    "B": 8,
    "policy": "entropy_bot_B_pt",
    "signal_kind": "per_trajectory_signal",
    "signal_name": "entropy",
    "allocation_policy": "bottom_B",
    "G": 0.43268537521362305,
    "A": 0.6080269813537598,
    "residual": -0.17534160614013672,
    "f_base": -4.862257957458496,
    "f_schedule": -4.429572582244873,
    "schedule_steps": [
      38,
      42,
      50,
      51,
      52,
      54,
      55,
      58
    ],
    "budget": 8,
    "wall_time": 13.291549921035767
  },
  {
    "seed": 71,
    "B": 8,
    "policy": "margin_top_B_pt",
    "signal_kind": "per_trajectory_signal",
    "signal_name": "inverse_margin",
    "allocation_policy": "top_B",
    "G": -0.19441795349121094,
    "A": 0.1942882537841797,
    "residual": -0.3887062072753906,
    "f_base": -4.862257957458496,
    "f_schedule": -5.056675910949707,
    "schedule_steps": [
      0,
      1,
      2,
      3,
      4,
      5,
      6,
      9
    ],
    "budget": 8,
    "wall_time": 13.294223308563232
  },
  {
    "seed": 71,
    "B": 8,
    "policy": "quality_top_B_pt",
    "signal_kind": "per_trajectory_signal",
    "signal_name": "quality_mass_proxy",
    "allocation_policy": "top_B",
    "G": -0.19441795349121094,
    "A": 0.1942882537841797,
    "residual": -0.3887062072753906,
    "f_base": -4.862257957458496,
    "f_schedule": -5.056675910949707,
    "schedule_steps": [
      0,
      1,
      2,
      3,
      4,
      5,
      6,
      9
    ],
    "budget": 8,
    "wall_time": 13.293830871582031
  },
  {
    "seed": 71,
    "B": 8,
    "policy": "entropy_top_B_mp",
    "signal_kind": "mean_profile_signal",
    "signal_name": "entropy",
    "allocation_policy": "top_B",
    "G": 0.10511159896850586,
    "A": -0.4525008201599121,
    "residual": 0.557612419128418,
    "f_base": -4.862257957458496,
    "f_schedule": -4.75714635848999,
    "schedule_steps": [
      0,
      1,
      2,
      3,
      4,
      5,
      6,
      7
    ],
    "budget": 8,
    "wall_time": 13.295733213424683
  },
  {
    "seed": 71,
    "B": 8,
    "policy": "mean_delta_oracle",
    "signal_kind": "mean_delta",
    "signal_name": null,
    "allocation_policy": "top_B",
    "G": 0.5326170921325684,
    "A": 0.9672255516052246,
    "residual": -0.43460845947265625,
    "f_base": -4.862257957458496,
    "f_schedule": -4.329640865325928,
    "schedule_steps": [
      11,
      23,
      25,
      28,
      29,
      31,
      40,
      41
    ],
    "budget": 8,
    "wall_time": 13.295008420944214
  },
  {
    "seed": 71,
    "B": 16,
    "policy": "uniform",
    "signal_kind": "none",
    "signal_name": null,
    "allocation_policy": "uniform",
    "G": 0.9298098087310791,
    "A": 1.2368826866149902,
    "residual": -0.30707287788391113,
    "f_base": -4.862257957458496,
    "f_schedule": -3.932448148727417,
    "schedule_steps": [
      0,
      4,
      8,
      12,
      16,
      20,
      24,
      28,
      32,
      36,
      40,
      44,
      48,
      52,
      56,
      60
    ],
    "budget": 16,
    "wall_time": 14.050375938415527
  },
  {
    "seed": 71,
    "B": 16,
    "policy": "front",
    "signal_kind": "none",
    "signal_name": null,
    "allocation_policy": "front",
    "G": 0.30911827087402344,
    "A": 0.43727731704711914,
    "residual": -0.1281590461730957,
    "f_base": -4.862257957458496,
    "f_schedule": -4.553139686584473,
    "schedule_steps": [
      0,
      1,
      2,
      3,
      4,
      5,
      6,
      7,
      8,
      9,
      10,
      11,
      12,
      13,
      14,
      15
    ],
    "budget": 16,
    "wall_time": 14.047002077102661
  },
  {
    "seed": 71,
    "B": 16,
    "policy": "back",
    "signal_kind": "none",
    "signal_name": null,
    "allocation_policy": "back",
    "G": 0.4255080223083496,
    "A": 1.1345019340515137,
    "residual": -0.7089939117431641,
    "f_base": -4.862257957458496,
    "f_schedule": -4.4367499351501465,
    "schedule_steps": [
      48,
      49,
      50,
      51,
      52,
      53,
      54,
      55,
      56,
      57,
      58,
      59,
      60,
      61,
      62,
      63
    ],
    "budget": 16,
    "wall_time": 14.051260709762573
  },
  {
    "seed": 71,
    "B": 16,
    "policy": "middle",
    "signal_kind": "none",
    "signal_name": null,
    "allocation_policy": "middle",
    "G": 0.728370189666748,
    "A": 1.5861926078796387,
    "residual": -0.8578224182128906,
    "f_base": -4.862257957458496,
    "f_schedule": -4.133887767791748,
    "schedule_steps": [
      24,
      25,
      26,
      27,
      28,
      29,
      30,
      31,
      32,
      33,
      34,
      35,
      36,
      37,
      38,
      39
    ],
    "budget": 16,
    "wall_time": 14.047590732574463
  },
  {
    "seed": 71,
    "B": 16,
    "policy": "entropy_top_B_pt",
    "signal_kind": "per_trajectory_signal",
    "signal_name": "entropy",
    "allocation_policy": "top_B",
    "G": 0.6048250198364258,
    "A": 0.2422776222229004,
    "residual": 0.3625473976135254,
    "f_base": -4.862257957458496,
    "f_schedule": -4.25743293762207,
    "schedule_steps": [
      0,
      1,
      2,
      3,
      4,
      5,
      6,
      7,
      8,
      9,
      10,
      11,
      13,
      14,
      22,
      63
    ],
    "budget": 16,
    "wall_time": 14.049323558807373
  },
  {
    "seed": 71,
    "B": 16,
    "policy": "entropy_bot_B_pt",
    "signal_kind": "per_trajectory_signal",
    "signal_name": "entropy",
    "allocation_policy": "bottom_B",
    "G": 0.5848565101623535,
    "A": 1.2363495826721191,
    "residual": -0.6514930725097656,
    "f_base": -4.862257957458496,
    "f_schedule": -4.277401447296143,
    "schedule_steps": [
      15,
      30,
      37,
      38,
      41,
      42,
      43,
      47,
      50,
      51,
      52,
      54,
      55,
      56,
      57,
      58
    ],
    "budget": 16,
    "wall_time": 14.047703504562378
  },
  {
    "seed": 71,
    "B": 16,
    "policy": "margin_top_B_pt",
    "signal_kind": "per_trajectory_signal",
    "signal_name": "inverse_margin",
    "allocation_policy": "top_B",
    "G": 0.6048250198364258,
    "A": 0.2422776222229004,
    "residual": 0.3625473976135254,
    "f_base": -4.862257957458496,
    "f_schedule": -4.25743293762207,
    "schedule_steps": [
      0,
      1,
      2,
      3,
      4,
      5,
      6,
      7,
      8,
      9,
      10,
      11,
      13,
      14,
      22,
      63
    ],
    "budget": 16,
    "wall_time": 14.048492193222046
  },
  {
    "seed": 71,
    "B": 16,
    "policy": "quality_top_B_pt",
    "signal_kind": "per_trajectory_signal",
    "signal_name": "quality_mass_proxy",
    "allocation_policy": "top_B",
    "G": 0.25962305068969727,
    "A": 0.29473400115966797,
    "residual": -0.0351109504699707,
    "f_base": -4.862257957458496,
    "f_schedule": -4.602634906768799,
    "schedule_steps": [
      0,
      1,
      2,
      3,
      4,
      5,
      6,
      7,
      8,
      9,
      10,
      11,
      13,
      14,
      16,
      63
    ],
    "budget": 16,
    "wall_time": 14.046885013580322
  },
  {
    "seed": 71,
    "B": 16,
    "policy": "entropy_top_B_mp",
    "signal_kind": "mean_profile_signal",
    "signal_name": "entropy",
    "allocation_policy": "top_B",
    "G": 0.49369049072265625,
    "A": 0.6588821411132812,
    "residual": -0.165191650390625,
    "f_base": -4.862257957458496,
    "f_schedule": -4.36856746673584,
    "schedule_steps": [
      0,
      1,
      2,
      3,
      4,
      5,
      6,
      7,
      8,
      9,
      10,
      11,
      12,
      13,
      14,
      63
    ],
    "budget": 16,
    "wall_time": 14.048750877380371
  },
  {
    "seed": 71,
    "B": 16,
    "policy": "mean_delta_oracle",
    "signal_kind": "mean_delta",
    "signal_name": null,
    "allocation_policy": "top_B",
    "G": 0.8360686302185059,
    "A": 1.8912444114685059,
    "residual": -1.05517578125,
    "f_base": -4.862257957458496,
    "f_schedule": -4.02618932723999,
    "schedule_steps": [
      11,
      12,
      20,
      23,
      24,
      25,
      27,
      28,
      29,
      30,
      31,
      39,
      40,
      41,
      42,
      43
    ],
    "budget": 16,
    "wall_time": 14.049386739730835
  }
]